[
  {
    "상세시설ID": 1,
    "상세시설명": "강당"
  },
  {
    "상세시설ID": 2,
    "상세시설명": "체육관"
  },
  {
    "상세시설ID": 3,
    "상세시설명": "1층 체육관(2층 관람석 제외)"
  },
  {
    "상세시설ID": 4,
    "상세시설명": "2층 체육관"
  },
  {
    "상세시설ID": 5,
    "상세시설명": "3층 체육관"
  },
  {
    "상세시설ID": 6,
    "상세시설명": "별관 2층 다목적 강당"
  },
  {
    "상세시설ID": 7,
    "상세시설명": "2층강당"
  },
  {
    "상세시설ID": 8,
    "상세시설명": "강당동 1층 강당"
  },
  {
    "상세시설ID": 9,
    "상세시설명": "교사동"
  },
  {
    "상세시설ID": 10,
    "상세시설명": "본관동"
  },
  {
    "상세시설ID": 11,
    "상세시설명": "강당(4층)"
  },
  {
    "상세시설ID": 12,
    "상세시설명": "체육관(본관)"
  },
  {
    "상세시설ID": 13,
    "상세시설명": "강당(2층)"
  },
  {
    "상세시설ID": 14,
    "상세시설명": "다목적강당"
  },
  {
    "상세시설ID": 15,
    "상세시설명": "회의실(2층)"
  },
  {
    "상세시설ID": 16,
    "상세시설명": "다목적강당(지하1층)"
  },
  {
    "상세시설ID": 17,
    "상세시설명": "정보센터"
  },
  {
    "상세시설ID": 18,
    "상세시설명": "강당(5층)"
  },
  {
    "상세시설ID": 19,
    "상세시설명": "헤오름관"
  },
  {
    "상세시설ID": 20,
    "상세시설명": "정보화센터"
  },
  {
    "상세시설ID": 21,
    "상세시설명": "3층 강당"
  },
  {
    "상세시설ID": 22,
    "상세시설명": "2층 회의실, 프로그램실"
  },
  {
    "상세시설ID": 23,
    "상세시설명": "2층 회의실, 3층 다목적실"
  },
  {
    "상세시설ID": 24,
    "상세시설명": "강당(3층)"
  },
  {
    "상세시설ID": 25,
    "상세시설명": "4층"
  },
  {
    "상세시설ID": 26,
    "상세시설명": "2층 강당"
  },
  {
    "상세시설ID": 27,
    "상세시설명": "3층 대회의실"
  },
  {
    "상세시설ID": 28,
    "상세시설명": "2층 대회의실"
  },
  {
    "상세시설ID": 29,
    "상세시설명": "1층 강당, 4층 다목적실"
  },
  {
    "상세시설ID": 30,
    "상세시설명": "1층 강의실, 2층 회의실"
  },
  {
    "상세시설ID": 31,
    "상세시설명": "1층"
  },
  {
    "상세시설ID": 32,
    "상세시설명": "2층 회의실"
  },
  {
    "상세시설ID": 33,
    "상세시설명": "해솔관(체육관)"
  },
  {
    "상세시설ID": 34,
    "상세시설명": "다목적체육관"
  },
  {
    "상세시설ID": 35,
    "상세시설명": "5층 다목적체육관"
  },
  {
    "상세시설ID": 36,
    "상세시설명": "대덕문화체육관"
  },
  {
    "상세시설ID": 37,
    "상세시설명": "5층 강당"
  },
  {
    "상세시설ID": 38,
    "상세시설명": "교사동 2층 강당"
  },
  {
    "상세시설ID": 39,
    "상세시설명": "교사동(A동) 1층"
  },
  {
    "상세시설ID": 40,
    "상세시설명": "강당, 특별활동실(2~3층)"
  },
  {
    "상세시설ID": 41,
    "상세시설명": "1본관 1~3층"
  },
  {
    "상세시설ID": 42,
    "상세시설명": "교실 및 강당"
  },
  {
    "상세시설ID": 43,
    "상세시설명": "산엔청복지관 분관 본관"
  },
  {
    "상세시설ID": 44,
    "상세시설명": "다목적실"
  },
  {
    "상세시설ID": 45,
    "상세시설명": "급식실,다목적실"
  },
  {
    "상세시설ID": 46,
    "상세시설명": "교사동(3동)"
  },
  {
    "상세시설ID": 47,
    "상세시설명": "경로당"
  },
  {
    "상세시설ID": 48,
    "상세시설명": "체육관동 2층"
  },
  {
    "상세시설ID": 49,
    "상세시설명": "산청고등학교 기숙사"
  },
  {
    "상세시설ID": 50,
    "상세시설명": "산엔청복지관 3층 다목적강당"
  },
  {
    "상세시설ID": 51,
    "상세시설명": "농업기술센터 미래생명관 2, 3층"
  },
  {
    "상세시설ID": 52,
    "상세시설명": "지리산권 사회복지관 1층 숙박시설 및 2층 다"
  },
  {
    "상세시설ID": 53,
    "상세시설명": "강당(체육관)"
  },
  {
    "상세시설ID": 54,
    "상세시설명": "문예회관"
  },
  {
    "상세시설ID": 55,
    "상세시설명": "본관 교실"
  },
  {
    "상세시설ID": 56,
    "상세시설명": "시청각실"
  },
  {
    "상세시설ID": 57,
    "상세시설명": "음악실"
  },
  {
    "상세시설ID": 58,
    "상세시설명": "미술실"
  },
  {
    "상세시설ID": 59,
    "상세시설명": "교사동(B동)1~3층"
  },
  {
    "상세시설ID": 60,
    "상세시설명": "너른교실"
  },
  {
    "상세시설ID": 61,
    "상세시설명": "실내체육관"
  },
  {
    "상세시설ID": 62,
    "상세시설명": "별관교실"
  },
  {
    "상세시설ID": 63,
    "상세시설명": "체육센터"
  },
  {
    "상세시설ID": 64,
    "상세시설명": "꽃우물수영장"
  },
  {
    "상세시설ID": 65,
    "상세시설명": "실내체육실"
  },
  {
    "상세시설ID": 66,
    "상세시설명": "본관 3층체육관"
  },
  {
    "상세시설ID": 67,
    "상세시설명": "다목적강당실"
  },
  {
    "상세시설ID": 68,
    "상세시설명": "특별교실"
  },
  {
    "상세시설ID": 69,
    "상세시설명": "급식식당"
  },
  {
    "상세시설ID": 70,
    "상세시설명": "의성군 청소년센터"
  },
  {
    "상세시설ID": 71,
    "상세시설명": "체력단련실"
  },
  {
    "상세시설ID": 72,
    "상세시설명": "다목적 강당"
  },
  {
    "상세시설ID": 73,
    "상세시설명": "강당(F동)"
  },
  {
    "상세시설ID": 74,
    "상세시설명": "의성군 게이트볼장"
  },
  {
    "상세시설ID": 75,
    "상세시설명": "다목적실(체육관)"
  },
  {
    "상세시설ID": 76,
    "상세시설명": "체육관(교실)"
  },
  {
    "상세시설ID": 77,
    "상세시설명": "본관교실"
  },
  {
    "상세시설ID": 78,
    "상세시설명": "연수원"
  },
  {
    "상세시설ID": 79,
    "상세시설명": "소강당"
  },
  {
    "상세시설ID": 80,
    "상세시설명": "4층 강당"
  },
  {
    "상세시설ID": 81,
    "상세시설명": "본관"
  },
  {
    "상세시설ID": 82,
    "상세시설명": "3층 실내제육관"
  },
  {
    "상세시설ID": 83,
    "상세시설명": "본관 4층 강당"
  },
  {
    "상세시설ID": 84,
    "상세시설명": "필승관(체육관)"
  },
  {
    "상세시설ID": 85,
    "상세시설명": "의성국민체육센터"
  },
  {
    "상세시설ID": 86,
    "상세시설명": "민간숙박시설"
  },
  {
    "상세시설ID": 87,
    "상세시설명": "의성군노인복지관"
  },
  {
    "상세시설ID": 88,
    "상세시설명": "의성군 조문국박물관"
  },
  {
    "상세시설ID": 89,
    "상세시설명": "대강당"
  },
  {
    "상세시설ID": 90,
    "상세시설명": "객실"
  },
  {
    "상세시설ID": 91,
    "상세시설명": "후관 2층 강당"
  },
  {
    "상세시설ID": 92,
    "상세시설명": "1층 체육관(관람석 제외)"
  },
  {
    "상세시설ID": 93,
    "상세시설명": "3층 다목적실"
  },
  {
    "상세시설ID": 94,
    "상세시설명": "교육관(다목적홀)"
  },
  {
    "상세시설ID": 95,
    "상세시설명": "1층 체육관"
  },
  {
    "상세시설ID": 96,
    "상세시설명": "3층 체육관(다목적 강당)"
  },
  {
    "상세시설ID": 97,
    "상세시설명": "2, 3층"
  },
  {
    "상세시설ID": 98,
    "상세시설명": "3층 회의실"
  },
  {
    "상세시설ID": 99,
    "상세시설명": "본관동 2층 강당"
  },
  {
    "상세시설ID": 100,
    "상세시설명": "달성군노인복지관"
  },
  {
    "상세시설ID": 101,
    "상세시설명": "주민건강증진센터"
  },
  {
    "상세시설ID": 102,
    "상세시설명": "다목적교실동 3층 강당"
  },
  {
    "상세시설ID": 103,
    "상세시설명": "강당동 2층 강당"
  },
  {
    "상세시설ID": 104,
    "상세시설명": "강당3동 3층 강당"
  },
  {
    "상세시설ID": 105,
    "상세시설명": "본관동 3층 강당"
  },
  {
    "상세시설ID": 106,
    "상세시설명": "교사동 3층 강당"
  },
  {
    "상세시설ID": 107,
    "상세시설명": "의회동"
  },
  {
    "상세시설ID": 108,
    "상세시설명": "문화복지동"
  },
  {
    "상세시설ID": 109,
    "상세시설명": "강당(별개 건물)"
  },
  {
    "상세시설ID": 110,
    "상세시설명": "기숙사동 3-5층 생활시설"
  },
  {
    "상세시설ID": 111,
    "상세시설명": "체육관동 2층 체육관"
  },
  {
    "상세시설ID": 112,
    "상세시설명": "달성국민체육센터"
  },
  {
    "상세시설ID": 113,
    "상세시설명": "달성종합스포츠파크"
  },
  {
    "상세시설ID": 114,
    "상세시설명": "태아관동 1층 강당"
  },
  {
    "상세시설ID": 115,
    "상세시설명": "달성군민체육관"
  },
  {
    "상세시설ID": 116,
    "상세시설명": "용기관 2층 강당"
  },
  {
    "상세시설ID": 117,
    "상세시설명": "6동 다목적강당"
  },
  {
    "상세시설ID": 118,
    "상세시설명": "지능형자동차부품진흥원"
  },
  {
    "상세시설ID": 119,
    "상세시설명": "기숙사동 4-5층 생활시설"
  },
  {
    "상세시설ID": 120,
    "상세시설명": "한국자동차연구원"
  },
  {
    "상세시설ID": 121,
    "상세시설명": "강당(본관5층)"
  },
  {
    "상세시설ID": 122,
    "상세시설명": "강당(본관2층)"
  },
  {
    "상세시설ID": 123,
    "상세시설명": "기숙사동 2-6층 생활시설"
  },
  {
    "상세시설ID": 124,
    "상세시설명": "본관동 2층 체육관"
  },
  {
    "상세시설ID": 125,
    "상세시설명": "다사읍사무소"
  },
  {
    "상세시설ID": 126,
    "상세시설명": "달성문화센터"
  },
  {
    "상세시설ID": 127,
    "상세시설명": "체육관(1층)"
  },
  {
    "상세시설ID": 128,
    "상세시설명": "강당(2층,5층)"
  },
  {
    "상세시설ID": 129,
    "상세시설명": "60호실"
  },
  {
    "상세시설ID": 130,
    "상세시설명": "30호실"
  },
  {
    "상세시설ID": 131,
    "상세시설명": "강당(본관4층)"
  },
  {
    "상세시설ID": 132,
    "상세시설명": "강당(별관 2층)"
  },
  {
    "상세시설ID": 133,
    "상세시설명": "강당(교내3층)"
  },
  {
    "상세시설ID": 134,
    "상세시설명": "강당(별개의 건물)"
  },
  {
    "상세시설ID": 135,
    "상세시설명": "산디관"
  },
  {
    "상세시설ID": 136,
    "상세시설명": "체육관 2층"
  },
  {
    "상세시설ID": 137,
    "상세시설명": "경암체육관"
  },
  {
    "상세시설ID": 138,
    "상세시설명": "체육관(2층)"
  },
  {
    "상세시설ID": 139,
    "상세시설명": "민락초등학교 강당"
  },
  {
    "상세시설ID": 140,
    "상세시설명": "본관 3층 체육관"
  },
  {
    "상세시설ID": 141,
    "상세시설명": "3층 대회의실, 2층 소회의실"
  },
  {
    "상세시설ID": 142,
    "상세시설명": "별관 다목적 체육관, 교사1,2동"
  },
  {
    "상세시설ID": 143,
    "상세시설명": "지상 1층, 2층"
  },
  {
    "상세시설ID": 144,
    "상세시설명": "문수체육관"
  },
  {
    "상세시설ID": 145,
    "상세시설명": "오곡면사무소2층"
  },
  {
    "상세시설ID": 146,
    "상세시설명": "4층 대회의실"
  },
  {
    "상세시설ID": 147,
    "상세시설명": "본관 2~3층 다목적 체육관"
  },
  {
    "상세시설ID": 148,
    "상세시설명": "통합동 2층 체육관"
  },
  {
    "상세시설ID": 149,
    "상세시설명": "별관 1층 다목적체육관"
  },
  {
    "상세시설ID": 150,
    "상세시설명": "3층 대회의실 및 지하1층 다목적홀"
  },
  {
    "상세시설ID": 151,
    "상세시설명": "대회의실 (3층)"
  },
  {
    "상세시설ID": 152,
    "상세시설명": "댄스연습실,GX룸(2층)"
  },
  {
    "상세시설ID": 153,
    "상세시설명": "행정동"
  },
  {
    "상세시설ID": 154,
    "상세시설명": "달성군청소년센터"
  },
  {
    "상세시설ID": 155,
    "상세시설명": "강당동 3층 강당"
  },
  {
    "상세시설ID": 156,
    "상세시설명": "4층 대강당"
  },
  {
    "상세시설ID": 157,
    "상세시설명": "본관 2층 체육관"
  },
  {
    "상세시설ID": 158,
    "상세시설명": "2층 소회의실, 3층 대회의실"
  },
  {
    "상세시설ID": 159,
    "상세시설명": "본관 1~5층 교실"
  },
  {
    "상세시설ID": 160,
    "상세시설명": "다목적강당(별도건물 2층)"
  },
  {
    "상세시설ID": 161,
    "상세시설명": "2층 다목적 강당"
  },
  {
    "상세시설ID": 162,
    "상세시설명": "다목적교실동"
  },
  {
    "상세시설ID": 163,
    "상세시설명": "다목적강당동"
  },
  {
    "상세시설ID": 164,
    "상세시설명": "강당동"
  },
  {
    "상세시설ID": 165,
    "상세시설명": "3동 다목적강당동"
  },
  {
    "상세시설ID": 166,
    "상세시설명": "라동 일용체육관동"
  },
  {
    "상세시설ID": 167,
    "상세시설명": "강당(2,3층)"
  },
  {
    "상세시설ID": 168,
    "상세시설명": "꿈나래관, 체육관"
  },
  {
    "상세시설ID": 169,
    "상세시설명": "강당(본관 4층)"
  },
  {
    "상세시설ID": 170,
    "상세시설명": "강당(8층)"
  },
  {
    "상세시설ID": 171,
    "상세시설명": "회의실"
  },
  {
    "상세시설ID": 172,
    "상세시설명": "급식소"
  },
  {
    "상세시설ID": 173,
    "상세시설명": "장기황어체육관"
  },
  {
    "상세시설ID": 174,
    "상세시설명": "동 행정복지센터"
  },
  {
    "상세시설ID": 175,
    "상세시설명": "체육관동"
  },
  {
    "상세시설ID": 176,
    "상세시설명": "급식동"
  },
  {
    "상세시설ID": 177,
    "상세시설명": "다목적교실"
  },
  {
    "상세시설ID": 178,
    "상세시설명": "대피시설"
  },
  {
    "상세시설ID": 179,
    "상세시설명": "1층(여), 2층(남)"
  },
  {
    "상세시설ID": 180,
    "상세시설명": "강당(교사동 2층)"
  },
  {
    "상세시설ID": 181,
    "상세시설명": "다목적실(교사동 4층)"
  },
  {
    "상세시설ID": 182,
    "상세시설명": "강당(교사동 1층)"
  },
  {
    "상세시설ID": 183,
    "상세시설명": "강당(교사동2층)"
  },
  {
    "상세시설ID": 184,
    "상세시설명": "강당(교사2동 3층)"
  },
  {
    "상세시설ID": 185,
    "상세시설명": "본당(3층)"
  },
  {
    "상세시설ID": 186,
    "상세시설명": "전시실(지하1층)"
  },
  {
    "상세시설ID": 187,
    "상세시설명": "88실"
  },
  {
    "상세시설ID": 188,
    "상세시설명": "종합체육관"
  },
  {
    "상세시설ID": 189,
    "상세시설명": "연습실"
  },
  {
    "상세시설ID": 190,
    "상세시설명": "갤러리"
  },
  {
    "상세시설ID": 191,
    "상세시설명": "소극장"
  },
  {
    "상세시설ID": 192,
    "상세시설명": "스튜디오3"
  },
  {
    "상세시설ID": 193,
    "상세시설명": "나래관 강당(2층)"
  },
  {
    "상세시설ID": 194,
    "상세시설명": "교사동,강당(2층)"
  },
  {
    "상세시설ID": 195,
    "상세시설명": "교사동,급식소,강당(2동 2층)"
  },
  {
    "상세시설ID": 196,
    "상세시설명": "지하1층 다목적체육실"
  },
  {
    "상세시설ID": 197,
    "상세시설명": "전체"
  },
  {
    "상세시설ID": 198,
    "상세시설명": "1층 대회의실"
  },
  {
    "상세시설ID": 199,
    "상세시설명": "급식실"
  },
  {
    "상세시설ID": 200,
    "상세시설명": "1층 대강당"
  },
  {
    "상세시설ID": 201,
    "상세시설명": "지하1층 생활체육실"
  },
  {
    "상세시설ID": 202,
    "상세시설명": "가동교사 2층 다목적실"
  },
  {
    "상세시설ID": 203,
    "상세시설명": "2층 강의실"
  },
  {
    "상세시설ID": 204,
    "상세시설명": "별관 지하1층"
  },
  {
    "상세시설ID": 205,
    "상세시설명": "교사1동 1층내 강당"
  },
  {
    "상세시설ID": 206,
    "상세시설명": "3층 대강당"
  },
  {
    "상세시설ID": 207,
    "상세시설명": "강당 (본관 3층)"
  },
  {
    "상세시설ID": 208,
    "상세시설명": "강당(지하1층)"
  },
  {
    "상세시설ID": 209,
    "상세시설명": "대강당(3층)"
  },
  {
    "상세시설ID": 210,
    "상세시설명": "체육관(3층 다목적관)"
  },
  {
    "상세시설ID": 211,
    "상세시설명": "체육관(3층)"
  },
  {
    "상세시설ID": 212,
    "상세시설명": "다목적홀(3층)"
  },
  {
    "상세시설ID": 213,
    "상세시설명": "학습관"
  },
  {
    "상세시설ID": 214,
    "상세시설명": "강당(소뫼관)"
  },
  {
    "상세시설ID": 215,
    "상세시설명": "후관동"
  },
  {
    "상세시설ID": 216,
    "상세시설명": "다목적회관(강당)"
  },
  {
    "상세시설ID": 217,
    "상세시설명": "북부노인복지관"
  },
  {
    "상세시설ID": 218,
    "상세시설명": "한국기계연구원"
  },
  {
    "상세시설ID": 219,
    "상세시설명": "본관 3층 강당"
  },
  {
    "상세시설ID": 220,
    "상세시설명": "유가읍사무소"
  },
  {
    "상세시설ID": 221,
    "상세시설명": "후관동 3층 강당"
  },
  {
    "상세시설ID": 222,
    "상세시설명": "실습4동"
  },
  {
    "상세시설ID": 223,
    "상세시설명": "씨름장"
  },
  {
    "상세시설ID": 224,
    "상세시설명": "체육관(지하 1층)"
  },
  {
    "상세시설ID": 225,
    "상세시설명": "대회의실 (본관 2층)"
  },
  {
    "상세시설ID": 226,
    "상세시설명": "4층 체육관"
  },
  {
    "상세시설ID": 227,
    "상세시설명": "조암9리경로당"
  },
  {
    "상세시설ID": 228,
    "상세시설명": "5층 체육관"
  },
  {
    "상세시설ID": 229,
    "상세시설명": "본관 3층"
  },
  {
    "상세시설ID": 230,
    "상세시설명": "1층 강당 및 대기실"
  },
  {
    "상세시설ID": 231,
    "상세시설명": "다목적실(4F)"
  },
  {
    "상세시설ID": 232,
    "상세시설명": "체육관(본관동 3층)"
  },
  {
    "상세시설ID": 233,
    "상세시설명": "체육관(본관동 5층)"
  },
  {
    "상세시설ID": 234,
    "상세시설명": "체육관(라동)"
  },
  {
    "상세시설ID": 235,
    "상세시설명": "학생식당(급식동 2층)"
  },
  {
    "상세시설ID": 236,
    "상세시설명": "다목적실(본관동1F),체육관(체육관동 2F)"
  },
  {
    "상세시설ID": 237,
    "상세시설명": "경로당(1~2층)"
  },
  {
    "상세시설ID": 238,
    "상세시설명": "다목적강당(강당동 2층)"
  },
  {
    "상세시설ID": 239,
    "상세시설명": "소예배실(지하2층), 찬양대실(6층)"
  },
  {
    "상세시설ID": 240,
    "상세시설명": "다목적강당(본관동 5층)"
  },
  {
    "상세시설ID": 241,
    "상세시설명": "나동 체육관"
  },
  {
    "상세시설ID": 242,
    "상세시설명": "다목적 강당 3,4층"
  },
  {
    "상세시설ID": 243,
    "상세시설명": "본관동 전산교육실,양호실, 다목적실"
  },
  {
    "상세시설ID": 244,
    "상세시설명": "교사동2층 강당, 체육관"
  },
  {
    "상세시설ID": 245,
    "상세시설명": "유치원"
  },
  {
    "상세시설ID": 246,
    "상세시설명": "마을회관"
  },
  {
    "상세시설ID": 247,
    "상세시설명": "민간숙박"
  },
  {
    "상세시설ID": 248,
    "상세시설명": "2인실 객실"
  },
  {
    "상세시설ID": 249,
    "상세시설명": "교사동(본관) 3~4층"
  },
  {
    "상세시설ID": 250,
    "상세시설명": "체육관(별동)"
  },
  {
    "상세시설ID": 251,
    "상세시설명": "어울터(강당및체육관)"
  },
  {
    "상세시설ID": 252,
    "상세시설명": "유스호스텔 숙소동"
  },
  {
    "상세시설ID": 253,
    "상세시설명": "교사2호동 교실"
  },
  {
    "상세시설ID": 254,
    "상세시설명": "체육관(교사동2층)"
  },
  {
    "상세시설ID": 255,
    "상세시설명": "2층 다목적실(황곡누리관)"
  },
  {
    "상세시설ID": 256,
    "상세시설명": "4층 다목적실"
  },
  {
    "상세시설ID": 257,
    "상세시설명": "도담관(체육관)"
  },
  {
    "상세시설ID": 258,
    "상세시설명": "1층 탁구실(193.16㎡),3층 다목적실(1"
  },
  {
    "상세시설ID": 259,
    "상세시설명": "교사1호동 3층 체육관"
  },
  {
    "상세시설ID": 260,
    "상세시설명": "1층 예절실(101.25㎡), 4층 체육실(1"
  },
  {
    "상세시설ID": 261,
    "상세시설명": "3층 다목적강당"
  },
  {
    "상세시설ID": 262,
    "상세시설명": "금천 문화원 강당"
  },
  {
    "상세시설ID": 263,
    "상세시설명": "교육관 강당"
  },
  {
    "상세시설ID": 264,
    "상세시설명": "4층 문화관람실"
  },
  {
    "상세시설ID": 265,
    "상세시설명": "2층 다목적강당"
  },
  {
    "상세시설ID": 266,
    "상세시설명": "본관 목적강당"
  },
  {
    "상세시설ID": 267,
    "상세시설명": "5층 대강당"
  },
  {
    "상세시설ID": 268,
    "상세시설명": "취미교실,대회의실"
  },
  {
    "상세시설ID": 269,
    "상세시설명": "2층 중회의실"
  },
  {
    "상세시설ID": 270,
    "상세시설명": "1,2층"
  },
  {
    "상세시설ID": 271,
    "상세시설명": "1,2,3층"
  },
  {
    "상세시설ID": 272,
    "상세시설명": "2층 다목적실"
  },
  {
    "상세시설ID": 273,
    "상세시설명": "2층"
  },
  {
    "상세시설ID": 274,
    "상세시설명": "2층-3층"
  },
  {
    "상세시설ID": 275,
    "상세시설명": "3층"
  },
  {
    "상세시설ID": 276,
    "상세시설명": "곡반정경로당"
  },
  {
    "상세시설ID": 277,
    "상세시설명": "본관(남,여)"
  },
  {
    "상세시설ID": 278,
    "상세시설명": "대회의실,체력단련실 등"
  },
  {
    "상세시설ID": 279,
    "상세시설명": "1층 회의실"
  },
  {
    "상세시설ID": 280,
    "상세시설명": "스탠다드/트윈실"
  },
  {
    "상세시설ID": 281,
    "상세시설명": "교사동 등 전체"
  },
  {
    "상세시설ID": 282,
    "상세시설명": "다목적교실(강당)"
  },
  {
    "상세시설ID": 283,
    "상세시설명": "본관(2층 건물)"
  },
  {
    "상세시설ID": 284,
    "상세시설명": "2층 A동 체육관"
  },
  {
    "상세시설ID": 285,
    "상세시설명": "2층 실내체육관"
  },
  {
    "상세시설ID": 286,
    "상세시설명": "다목적체육관(12동)"
  },
  {
    "상세시설ID": 287,
    "상세시설명": "1~4층 교실"
  },
  {
    "상세시설ID": 288,
    "상세시설명": "별관 3층 체육관"
  },
  {
    "상세시설ID": 289,
    "상세시설명": "1~2층 교실, 1층 도서실, 1층 체육관"
  },
  {
    "상세시설ID": 290,
    "상세시설명": "2층 회의실, 노래교실"
  },
  {
    "상세시설ID": 291,
    "상세시설명": "별관 4층 체육관"
  },
  {
    "상세시설ID": 292,
    "상세시설명": "1~3층 교실"
  },
  {
    "상세시설ID": 293,
    "상세시설명": "체육관, 1~5층 교실"
  },
  {
    "상세시설ID": 294,
    "상세시설명": "5층 다목적 강당"
  },
  {
    "상세시설ID": 295,
    "상세시설명": "1~4층 본관, 별관 4층 체육관"
  },
  {
    "상세시설ID": 296,
    "상세시설명": "2층 체육관, 1~5층 교실, 별관 2~5층"
  },
  {
    "상세시설ID": 297,
    "상세시설명": "3층 8호동 체육관"
  },
  {
    "상세시설ID": 298,
    "상세시설명": "2층 대회의실, 3층 탁구장,풋살장, 프로그램"
  },
  {
    "상세시설ID": 299,
    "상세시설명": "3층 다목적 강당"
  },
  {
    "상세시설ID": 300,
    "상세시설명": "6층 다목적 강당"
  },
  {
    "상세시설ID": 301,
    "상세시설명": "2층 대회의실, 4층 다목적강당"
  },
  {
    "상세시설ID": 302,
    "상세시설명": "본관 1층 특수교실"
  },
  {
    "상세시설ID": 303,
    "상세시설명": "3~5층 교실"
  },
  {
    "상세시설ID": 304,
    "상세시설명": "2층 작은도서관, 2층 문화사랑방, 3층 회의"
  },
  {
    "상세시설ID": 305,
    "상세시설명": "B동 4~5층 체육관"
  },
  {
    "상세시설ID": 306,
    "상세시설명": "교육문화센터 4층 체육관"
  },
  {
    "상세시설ID": 307,
    "상세시설명": "7층 강당"
  },
  {
    "상세시설ID": 308,
    "상세시설명": "1층 본관"
  },
  {
    "상세시설ID": 309,
    "상세시설명": "귀인문화복지센터 4층 다목적실"
  },
  {
    "상세시설ID": 310,
    "상세시설명": "2층 다목적 체육관"
  },
  {
    "상세시설ID": 311,
    "상세시설명": "1층 다목적 체육관, 1~5층 교실"
  },
  {
    "상세시설ID": 312,
    "상세시설명": "4층 다목적 강당"
  },
  {
    "상세시설ID": 313,
    "상세시설명": "1층 민원실, 2층 회의실, 3층 다목적실,"
  },
  {
    "상세시설ID": 314,
    "상세시설명": "교실 1~3층"
  },
  {
    "상세시설ID": 315,
    "상세시설명": "경기도립노인전문 동두천병원"
  },
  {
    "상세시설ID": 316,
    "상세시설명": "교실 전체"
  },
  {
    "상세시설ID": 317,
    "상세시설명": "본관 교실 전체"
  },
  {
    "상세시설ID": 318,
    "상세시설명": "2층 생활체육실, 4층 대회의실"
  },
  {
    "상세시설ID": 319,
    "상세시설명": "동관동 체육관"
  },
  {
    "상세시설ID": 320,
    "상세시설명": "체육관 소피아홀"
  },
  {
    "상세시설ID": 321,
    "상세시설명": "강당동 3층"
  },
  {
    "상세시설ID": 322,
    "상세시설명": "1층 교실 일부"
  },
  {
    "상세시설ID": 323,
    "상세시설명": "1층 남자경로당"
  },
  {
    "상세시설ID": 324,
    "상세시설명": "2층 대강당"
  },
  {
    "상세시설ID": 325,
    "상세시설명": "1층 강당"
  },
  {
    "상세시설ID": 326,
    "상세시설명": "4층회의실"
  },
  {
    "상세시설ID": 327,
    "상세시설명": "생활관"
  },
  {
    "상세시설ID": 328,
    "상세시설명": "4층 다목적강당, 3층 체력단련실"
  },
  {
    "상세시설ID": 329,
    "상세시설명": "1층 경로당"
  },
  {
    "상세시설ID": 330,
    "상세시설명": "경기장"
  },
  {
    "상세시설ID": 331,
    "상세시설명": "4층 회의실"
  },
  {
    "상세시설ID": 332,
    "상세시설명": "예절관"
  },
  {
    "상세시설ID": 333,
    "상세시설명": "4층 다목적강당"
  },
  {
    "상세시설ID": 334,
    "상세시설명": "4층 체력단련실, 5층 대회의실"
  },
  {
    "상세시설ID": 335,
    "상세시설명": "상담실"
  },
  {
    "상세시설ID": 336,
    "상세시설명": "4층 강당, 3층 다목적실"
  },
  {
    "상세시설ID": 337,
    "상세시설명": "태양관,바다관"
  },
  {
    "상세시설ID": 338,
    "상세시설명": "갈매중학교 교사동 1층"
  },
  {
    "상세시설ID": 339,
    "상세시설명": "체육관,급식실"
  },
  {
    "상세시설ID": 340,
    "상세시설명": "본관 및 별관"
  },
  {
    "상세시설ID": 341,
    "상세시설명": "다목적 당당"
  },
  {
    "상세시설ID": 342,
    "상세시설명": "도서관"
  },
  {
    "상세시설ID": 343,
    "상세시설명": "교육관(3층)"
  },
  {
    "상세시설ID": 344,
    "상세시설명": "관공서"
  },
  {
    "상세시설ID": 345,
    "상세시설명": "교사동내(다목적실)"
  },
  {
    "상세시설ID": 346,
    "상세시설명": "병원"
  },
  {
    "상세시설ID": 347,
    "상세시설명": "2층 예배당"
  },
  {
    "상세시설ID": 348,
    "상세시설명": "복합문화센터(강당)"
  },
  {
    "상세시설ID": 349,
    "상세시설명": "체육관 지하1층"
  },
  {
    "상세시설ID": 350,
    "상세시설명": "강당 등"
  },
  {
    "상세시설ID": 351,
    "상세시설명": "다목적실, 숙소"
  },
  {
    "상세시설ID": 352,
    "상세시설명": "공공청사"
  },
  {
    "상세시설ID": 353,
    "상세시설명": "2층 배드민턴장"
  },
  {
    "상세시설ID": 354,
    "상세시설명": "3층 시청각실"
  },
  {
    "상세시설ID": 355,
    "상세시설명": "2층 문화교실"
  },
  {
    "상세시설ID": 356,
    "상세시설명": "강당(6층)"
  },
  {
    "상세시설ID": 357,
    "상세시설명": "대강당(2층)"
  },
  {
    "상세시설ID": 358,
    "상세시설명": "2층 소회의실"
  },
  {
    "상세시설ID": 359,
    "상세시설명": "대회의실"
  },
  {
    "상세시설ID": 360,
    "상세시설명": "순창쉴랜드하우스(숙박동)"
  },
  {
    "상세시설ID": 361,
    "상세시설명": "연수시설"
  },
  {
    "상세시설ID": 362,
    "상세시설명": "다목정강당"
  },
  {
    "상세시설ID": 363,
    "상세시설명": "3층 대회의실(대강의실)"
  },
  {
    "상세시설ID": 364,
    "상세시설명": "3층 세미나실"
  },
  {
    "상세시설ID": 365,
    "상세시설명": "동아리방, 세미나실"
  },
  {
    "상세시설ID": 366,
    "상세시설명": "산학문화관 2층세미나실"
  },
  {
    "상세시설ID": 367,
    "상세시설명": "강당 겸 체육관"
  },
  {
    "상세시설ID": 368,
    "상세시설명": "테니스장(1층)"
  },
  {
    "상세시설ID": 369,
    "상세시설명": "4층 강당(다목적실)"
  },
  {
    "상세시설ID": 370,
    "상세시설명": "1층 강당(생활체육실)"
  },
  {
    "상세시설ID": 371,
    "상세시설명": "1층 체육관, 회의실 및 다용도실"
  },
  {
    "상세시설ID": 372,
    "상세시설명": "1층 다목적실, 2층 프로그램실"
  },
  {
    "상세시설ID": 373,
    "상세시설명": "전체시설"
  },
  {
    "상세시설ID": 374,
    "상세시설명": "다목적회관"
  },
  {
    "상세시설ID": 375,
    "상세시설명": "고늘관"
  },
  {
    "상세시설ID": 376,
    "상세시설명": "오션뷰 호텔 객실"
  },
  {
    "상세시설ID": 377,
    "상세시설명": "백구관"
  },
  {
    "상세시설ID": 378,
    "상세시설명": "2층 보건교육실"
  },
  {
    "상세시설ID": 379,
    "상세시설명": "1층 소리교실, 2층 건강교실"
  },
  {
    "상세시설ID": 380,
    "상세시설명": "본관 1층"
  },
  {
    "상세시설ID": 381,
    "상세시설명": "1층 프로그램실/다목적홀"
  },
  {
    "상세시설ID": 382,
    "상세시설명": "1층 다목적실"
  },
  {
    "상세시설ID": 383,
    "상세시설명": "세미나실 등"
  },
  {
    "상세시설ID": 384,
    "상세시설명": "강당 3층"
  },
  {
    "상세시설ID": 385,
    "상세시설명": "굿모닝호텔 객실"
  },
  {
    "상세시설ID": 386,
    "상세시설명": "2층 대강당,프로그램실"
  },
  {
    "상세시설ID": 387,
    "상세시설명": "2층대왕암홀, 1층바드래홀"
  },
  {
    "상세시설ID": 388,
    "상세시설명": "2층다목적실, 3층강당"
  },
  {
    "상세시설ID": 389,
    "상세시설명": "체육관(명지관)"
  },
  {
    "상세시설ID": 390,
    "상세시설명": "공연장 연습실"
  },
  {
    "상세시설ID": 391,
    "상세시설명": "인터넷모텔"
  },
  {
    "상세시설ID": 392,
    "상세시설명": "세화모텔"
  },
  {
    "상세시설ID": 393,
    "상세시설명": "별관2층 체육관(군붕관)"
  },
  {
    "상세시설ID": 394,
    "상세시설명": "2인실 43호"
  },
  {
    "상세시설ID": 395,
    "상세시설명": "1층 체육관 (금강관)"
  },
  {
    "상세시설ID": 396,
    "상세시설명": "별관2층 강당(원예관)"
  },
  {
    "상세시설ID": 397,
    "상세시설명": "2인실 45호"
  },
  {
    "상세시설ID": 398,
    "상세시설명": "숙박시설"
  },
  {
    "상세시설ID": 399,
    "상세시설명": "강당(별관 솔마루))"
  },
  {
    "상세시설ID": 400,
    "상세시설명": "1층 소망홀"
  },
  {
    "상세시설ID": 401,
    "상세시설명": "4층 강당(아시아드 홀)"
  },
  {
    "상세시설ID": 402,
    "상세시설명": "별관외 건물 강당(신나래관)"
  },
  {
    "상세시설ID": 403,
    "상세시설명": "3층 강당(안진관)"
  },
  {
    "상세시설ID": 404,
    "상세시설명": "동역관 3층(체육관)"
  },
  {
    "상세시설ID": 405,
    "상세시설명": "J동 2층 수영장형 강당"
  },
  {
    "상세시설ID": 406,
    "상세시설명": "2층 강당(희망관)"
  },
  {
    "상세시설ID": 407,
    "상세시설명": "2층 다목적교실(한빛관)"
  },
  {
    "상세시설ID": 408,
    "상세시설명": "2층 강당(꿈마루관)"
  },
  {
    "상세시설ID": 409,
    "상세시설명": "2인실 38호"
  },
  {
    "상세시설ID": 410,
    "상세시설명": "2,3층 회의실"
  },
  {
    "상세시설ID": 411,
    "상세시설명": "2층 다목적교실(날뫼누리관)"
  },
  {
    "상세시설ID": 412,
    "상세시설명": "1,2,5층"
  },
  {
    "상세시설ID": 413,
    "상세시설명": "1층 다목적교실(서대구관)"
  },
  {
    "상세시설ID": 414,
    "상세시설명": "숭인1동주민센터3층"
  },
  {
    "상세시설ID": 415,
    "상세시설명": "4층강당"
  },
  {
    "상세시설ID": 416,
    "상세시설명": "프로그램실"
  },
  {
    "상세시설ID": 417,
    "상세시설명": "3층, 다목적실"
  },
  {
    "상세시설ID": 418,
    "상세시설명": "지하1층, 어울림방"
  },
  {
    "상세시설ID": 419,
    "상세시설명": "민간숙박업소"
  },
  {
    "상세시설ID": 420,
    "상세시설명": "2층 다목적교실(달인관)"
  },
  {
    "상세시설ID": 421,
    "상세시설명": "강당 4층"
  },
  {
    "상세시설ID": 422,
    "상세시설명": "교육장"
  },
  {
    "상세시설ID": 423,
    "상세시설명": "급식소동/다목적강당"
  },
  {
    "상세시설ID": 424,
    "상세시설명": "급식동 1층"
  },
  {
    "상세시설ID": 425,
    "상세시설명": "미래관"
  },
  {
    "상세시설ID": 426,
    "상세시설명": "신관동"
  },
  {
    "상세시설ID": 427,
    "상세시설명": "다목적강당(어울채)"
  },
  {
    "상세시설ID": 428,
    "상세시설명": "지하1층, 다목적실"
  },
  {
    "상세시설ID": 429,
    "상세시설명": "식당동"
  },
  {
    "상세시설ID": 430,
    "상세시설명": "대강당/체육관"
  },
  {
    "상세시설ID": 431,
    "상세시설명": "어련당"
  },
  {
    "상세시설ID": 432,
    "상세시설명": "본관동2층, 강당"
  },
  {
    "상세시설ID": 433,
    "상세시설명": "4층, 다목적실"
  },
  {
    "상세시설ID": 434,
    "상세시설명": "1층,다목적실(지하강당)"
  },
  {
    "상세시설ID": 435,
    "상세시설명": "3층, 다목적방"
  },
  {
    "상세시설ID": 436,
    "상세시설명": "2층, 다목적실"
  },
  {
    "상세시설ID": 437,
    "상세시설명": "1층, 체육관"
  },
  {
    "상세시설ID": 438,
    "상세시설명": "2층, 3층"
  },
  {
    "상세시설ID": 439,
    "상세시설명": "프로그램실-1(2층), 강당(3층)"
  },
  {
    "상세시설ID": 440,
    "상세시설명": "다목적실(3층)"
  },
  {
    "상세시설ID": 441,
    "상세시설명": "숙박실, 체육관, 다목적실"
  },
  {
    "상세시설ID": 442,
    "상세시설명": "교사2동/후관동"
  },
  {
    "상세시설ID": 443,
    "상세시설명": "다목적강당(5층)"
  },
  {
    "상세시설ID": 444,
    "상세시설명": "대강당(5층)"
  },
  {
    "상세시설ID": 445,
    "상세시설명": "다목적실(4층)"
  },
  {
    "상세시설ID": 446,
    "상세시설명": "2층, 회의실"
  },
  {
    "상세시설ID": 447,
    "상세시설명": "강당 겸 체육관동"
  },
  {
    "상세시설ID": 448,
    "상세시설명": "문화관(체육관)"
  },
  {
    "상세시설ID": 449,
    "상세시설명": "5층, 독서당"
  },
  {
    "상세시설ID": 450,
    "상세시설명": "음악연습실, 스포츠댄스실"
  },
  {
    "상세시설ID": 451,
    "상세시설명": "서울주문화센터(2층전시실)"
  },
  {
    "상세시설ID": 452,
    "상세시설명": "문화복지시설"
  },
  {
    "상세시설ID": 453,
    "상세시설명": "5층, 다목적방"
  },
  {
    "상세시설ID": 454,
    "상세시설명": "본관동2층, 체육관"
  },
  {
    "상세시설ID": 455,
    "상세시설명": "화양동주민센터"
  },
  {
    "상세시설ID": 456,
    "상세시설명": "광장동주민센터"
  },
  {
    "상세시설ID": 457,
    "상세시설명": "삼남초등학교"
  },
  {
    "상세시설ID": 458,
    "상세시설명": "2층 강당(일석헌)"
  },
  {
    "상세시설ID": 459,
    "상세시설명": "별관 3층 강당(라온누리)"
  },
  {
    "상세시설ID": 460,
    "상세시설명": "별관2층 강당(해랑관)"
  },
  {
    "상세시설ID": 461,
    "상세시설명": "2층 강당(꿈나무)"
  },
  {
    "상세시설ID": 462,
    "상세시설명": "2층 다목적교실(나래관)"
  },
  {
    "상세시설ID": 463,
    "상세시설명": "2층 청운관"
  },
  {
    "상세시설ID": 464,
    "상세시설명": "5층 대회의실"
  },
  {
    "상세시설ID": 465,
    "상세시설명": "봉화관"
  },
  {
    "상세시설ID": 466,
    "상세시설명": "체육관(동원마루)"
  },
  {
    "상세시설ID": 467,
    "상세시설명": "종합정보관"
  },
  {
    "상세시설ID": 468,
    "상세시설명": "도서관 건물"
  },
  {
    "상세시설ID": 469,
    "상세시설명": "별관 2층 강당(충비관)"
  },
  {
    "상세시설ID": 470,
    "상세시설명": "별관 2층 강당(안락마루)"
  },
  {
    "상세시설ID": 471,
    "상세시설명": "별관 2층 강당(청운관)"
  },
  {
    "상세시설ID": 472,
    "상세시설명": "지하1층"
  },
  {
    "상세시설ID": 473,
    "상세시설명": "정보화동 3층 강당"
  },
  {
    "상세시설ID": 474,
    "상세시설명": "지하2층"
  },
  {
    "상세시설ID": 475,
    "상세시설명": "신관"
  },
  {
    "상세시설ID": 476,
    "상세시설명": "다우리관"
  },
  {
    "상세시설ID": 477,
    "상세시설명": "체육관(봉화관)"
  },
  {
    "상세시설ID": 478,
    "상세시설명": "청사 본관"
  },
  {
    "상세시설ID": 479,
    "상세시설명": "체육관 1층"
  },
  {
    "상세시설ID": 480,
    "상세시설명": "체육관 및 특별교실"
  },
  {
    "상세시설ID": 481,
    "상세시설명": "서관동"
  },
  {
    "상세시설ID": 482,
    "상세시설명": "광양관동"
  },
  {
    "상세시설ID": 483,
    "상세시설명": "온누리관"
  },
  {
    "상세시설ID": 484,
    "상세시설명": "교육정보관동"
  },
  {
    "상세시설ID": 485,
    "상세시설명": "교사(본관동)"
  },
  {
    "상세시설ID": 486,
    "상세시설명": "다목적홀"
  },
  {
    "상세시설ID": 487,
    "상세시설명": "본관동(체육관), 교실"
  },
  {
    "상세시설ID": 488,
    "상세시설명": "본관 후관"
  },
  {
    "상세시설ID": 489,
    "상세시설명": "교실, 체육관"
  },
  {
    "상세시설ID": 490,
    "상세시설명": "전관(교실)"
  },
  {
    "상세시설ID": 491,
    "상세시설명": "자양2동주민센터"
  },
  {
    "상세시설ID": 492,
    "상세시설명": "교실,체육관"
  },
  {
    "상세시설ID": 493,
    "상세시설명": "교실"
  },
  {
    "상세시설ID": 494,
    "상세시설명": "다목적강당 1층"
  },
  {
    "상세시설ID": 495,
    "상세시설명": "1층, 2층"
  },
  {
    "상세시설ID": 496,
    "상세시설명": "한갓관"
  },
  {
    "상세시설ID": 497,
    "상세시설명": "스파뷰호텔"
  },
  {
    "상세시설ID": 498,
    "상세시설명": "수덕꿈나래 강당"
  },
  {
    "상세시설ID": 499,
    "상세시설명": "마을공동시설"
  },
  {
    "상세시설ID": 500,
    "상세시설명": "지하1층 대피소"
  },
  {
    "상세시설ID": 501,
    "상세시설명": "장례식장"
  },
  {
    "상세시설ID": 502,
    "상세시설명": "행복학습교실"
  },
  {
    "상세시설ID": 503,
    "상세시설명": "객실(내진적용은 155㎡, 127명)"
  },
  {
    "상세시설ID": 504,
    "상세시설명": "다목적강당(1층)"
  },
  {
    "상세시설ID": 505,
    "상세시설명": "문화강좌실, 숙소"
  },
  {
    "상세시설ID": 506,
    "상세시설명": "강당(본관3층)"
  },
  {
    "상세시설ID": 507,
    "상세시설명": "식당"
  },
  {
    "상세시설ID": 508,
    "상세시설명": "야구부생활관(2층)"
  },
  {
    "상세시설ID": 509,
    "상세시설명": "지하1층 다목적 강당"
  },
  {
    "상세시설ID": 510,
    "상세시설명": "4층 대강당, 소강당"
  },
  {
    "상세시설ID": 511,
    "상세시설명": "다목적강당(2층)"
  },
  {
    "상세시설ID": 512,
    "상세시설명": "2층 교육장"
  },
  {
    "상세시설ID": 513,
    "상세시설명": "별관"
  },
  {
    "상세시설ID": 514,
    "상세시설명": "강당1,교실40"
  },
  {
    "상세시설ID": 515,
    "상세시설명": "교실31"
  },
  {
    "상세시설ID": 516,
    "상세시설명": "5층 회의실"
  },
  {
    "상세시설ID": 517,
    "상세시설명": "급식시설"
  },
  {
    "상세시설ID": 518,
    "상세시설명": "동관, 서관"
  },
  {
    "상세시설ID": 519,
    "상세시설명": "3층 종합체육관"
  },
  {
    "상세시설ID": 520,
    "상세시설명": "교사동(E동)"
  },
  {
    "상세시설ID": 521,
    "상세시설명": "남관"
  },
  {
    "상세시설ID": 522,
    "상세시설명": "지하2층 체육관"
  },
  {
    "상세시설ID": 523,
    "상세시설명": "급식소 및 다목적 강당"
  },
  {
    "상세시설ID": 524,
    "상세시설명": "대회의실(안전교육장)"
  },
  {
    "상세시설ID": 525,
    "상세시설명": "체육관(별관3층)"
  },
  {
    "상세시설ID": 526,
    "상세시설명": "다목적강당(3층)"
  },
  {
    "상세시설ID": 527,
    "상세시설명": "체육관(별동2층)"
  },
  {
    "상세시설ID": 528,
    "상세시설명": "체육관(별관)"
  },
  {
    "상세시설ID": 529,
    "상세시설명": "목향관"
  },
  {
    "상세시설ID": 530,
    "상세시설명": "기숙사"
  },
  {
    "상세시설ID": 531,
    "상세시설명": "음악관"
  },
  {
    "상세시설ID": 532,
    "상세시설명": "무궁화관"
  },
  {
    "상세시설ID": 533,
    "상세시설명": "본관동 강의실"
  },
  {
    "상세시설ID": 534,
    "상세시설명": "수련원"
  },
  {
    "상세시설ID": 535,
    "상세시설명": "예지관"
  },
  {
    "상세시설ID": 536,
    "상세시설명": "교육연구시설"
  },
  {
    "상세시설ID": 537,
    "상세시설명": "배드민턴장"
  },
  {
    "상세시설ID": 538,
    "상세시설명": "선산청소년수련관 생활관"
  },
  {
    "상세시설ID": 539,
    "상세시설명": "돌봄교실"
  },
  {
    "상세시설ID": 540,
    "상세시설명": "남기숙사"
  },
  {
    "상세시설ID": 541,
    "상세시설명": "별관동"
  },
  {
    "상세시설ID": 542,
    "상세시설명": "매화어울관"
  },
  {
    "상세시설ID": 543,
    "상세시설명": "A동(교사동)"
  },
  {
    "상세시설ID": 544,
    "상세시설명": "D동(기숙사)"
  },
  {
    "상세시설ID": 545,
    "상세시설명": "급식소 및 강당"
  },
  {
    "상세시설ID": 546,
    "상세시설명": "후관"
  },
  {
    "상세시설ID": 547,
    "상세시설명": "급식소 1층"
  },
  {
    "상세시설ID": 548,
    "상세시설명": "기숙사(빛솔관)"
  },
  {
    "상세시설ID": 549,
    "상세시설명": "전자기계실습동"
  },
  {
    "상세시설ID": 550,
    "상세시설명": "강당 2,3층"
  },
  {
    "상세시설ID": 551,
    "상세시설명": "교육공동체실"
  },
  {
    "상세시설ID": 552,
    "상세시설명": "수성관(체육관)"
  },
  {
    "상세시설ID": 553,
    "상세시설명": "교사1호동(본관) 2층"
  },
  {
    "상세시설ID": 554,
    "상세시설명": "체육관(3층 다목적강당)"
  },
  {
    "상세시설ID": 555,
    "상세시설명": "3층 다목적홀"
  },
  {
    "상세시설ID": 556,
    "상세시설명": "실내승마장"
  },
  {
    "상세시설ID": 557,
    "상세시설명": "지하 강당"
  },
  {
    "상세시설ID": 558,
    "상세시설명": "구관"
  },
  {
    "상세시설ID": 559,
    "상세시설명": "체육관(양산관)"
  },
  {
    "상세시설ID": 560,
    "상세시설명": "수덕관(신축 기숙사)"
  },
  {
    "상세시설ID": 561,
    "상세시설명": "다목적강당(슬기관)"
  },
  {
    "상세시설ID": 562,
    "상세시설명": "다목적강당(북마루관)"
  },
  {
    "상세시설ID": 563,
    "상세시설명": "에어로빅,휴게실"
  },
  {
    "상세시설ID": 564,
    "상세시설명": "다목적강당(천마관)"
  },
  {
    "상세시설ID": 565,
    "상세시설명": "금산여고강당동"
  },
  {
    "상세시설ID": 566,
    "상세시설명": "금산종합체육관"
  },
  {
    "상세시설ID": 567,
    "상세시설명": "금산군 배드민턴장"
  },
  {
    "상세시설ID": 568,
    "상세시설명": "이슬공원 생활체육관"
  },
  {
    "상세시설ID": 569,
    "상세시설명": "5층(28실)"
  },
  {
    "상세시설ID": 570,
    "상세시설명": "5층(31실)"
  },
  {
    "상세시설ID": 571,
    "상세시설명": "방갈로(5동),펜션(2호)"
  },
  {
    "상세시설ID": 572,
    "상세시설명": "군북초강당동"
  },
  {
    "상세시설ID": 573,
    "상세시설명": "상곡초본관교사1"
  },
  {
    "상세시설ID": 574,
    "상세시설명": "상곡초급식동"
  },
  {
    "상세시설ID": 575,
    "상세시설명": "상곡초교사2"
  },
  {
    "상세시설ID": 576,
    "상세시설명": "남일초급식실동"
  },
  {
    "상세시설ID": 577,
    "상세시설명": "남이초급식실동"
  },
  {
    "상세시설ID": 578,
    "상세시설명": "금산인삼호텔"
  },
  {
    "상세시설ID": 579,
    "상세시설명": "금산군 테니스장"
  },
  {
    "상세시설ID": 580,
    "상세시설명": "금산초본관교사"
  },
  {
    "상세시설ID": 581,
    "상세시설명": "금산동중본관교사"
  },
  {
    "상세시설ID": 582,
    "상세시설명": "산업고강당"
  },
  {
    "상세시설ID": 583,
    "상세시설명": "금산여중급식실동"
  },
  {
    "상세시설ID": 584,
    "상세시설명": "금산여고 교사동1-2"
  },
  {
    "상세시설ID": 585,
    "상세시설명": "리베라모텔"
  },
  {
    "상세시설ID": 586,
    "상세시설명": "강당, 교실"
  },
  {
    "상세시설ID": 587,
    "상세시설명": "부여국민체육센터"
  },
  {
    "상세시설ID": 588,
    "상세시설명": "숙박시설 지상 10층"
  },
  {
    "상세시설ID": 589,
    "상세시설명": "숙박시설 지상2층"
  },
  {
    "상세시설ID": 590,
    "상세시설명": "2층강당, 2-4층 생활관"
  },
  {
    "상세시설ID": 591,
    "상세시설명": "강당(장암꿈나무관)"
  },
  {
    "상세시설ID": 592,
    "상세시설명": "별관 강당"
  },
  {
    "상세시설ID": 593,
    "상세시설명": "실내체육관(1,3층)"
  },
  {
    "상세시설ID": 594,
    "상세시설명": "제원중본관교사"
  },
  {
    "상세시설ID": 595,
    "상세시설명": "부리초급식실동"
  },
  {
    "상세시설ID": 596,
    "상세시설명": "용문초다목적강당"
  },
  {
    "상세시설ID": 597,
    "상세시설명": "강당(교사시설내 2층)"
  },
  {
    "상세시설ID": 598,
    "상세시설명": "기계과 실습동 3층"
  },
  {
    "상세시설ID": 599,
    "상세시설명": "본관 체육관"
  },
  {
    "상세시설ID": 600,
    "상세시설명": "신암면복지회관"
  },
  {
    "상세시설ID": 601,
    "상세시설명": "스플라스리솜"
  },
  {
    "상세시설ID": 602,
    "상세시설명": "2층회의실"
  },
  {
    "상세시설ID": 603,
    "상세시설명": "완도초등학교 다목적강당"
  },
  {
    "상세시설ID": 604,
    "상세시설명": "문화예술의 전당"
  },
  {
    "상세시설ID": 605,
    "상세시설명": "완도수고 수산교육관"
  },
  {
    "상세시설ID": 606,
    "상세시설명": "완도고 본관"
  },
  {
    "상세시설ID": 607,
    "상세시설명": "금일초 다목적강당"
  },
  {
    "상세시설ID": 608,
    "상세시설명": "노화고다목적강당"
  },
  {
    "상세시설ID": 609,
    "상세시설명": "넙도초다목적강당"
  },
  {
    "상세시설ID": 610,
    "상세시설명": "생영초다목적강당"
  },
  {
    "상세시설ID": 611,
    "상세시설명": "더베네치아스위트호텔"
  },
  {
    "상세시설ID": 612,
    "상세시설명": "교사동 다목적 강당"
  },
  {
    "상세시설ID": 613,
    "상세시설명": "다목적체육실"
  },
  {
    "상세시설ID": 614,
    "상세시설명": "장미관동 3층 강당"
  },
  {
    "상세시설ID": 615,
    "상세시설명": "지하1층 강당"
  },
  {
    "상세시설ID": 616,
    "상세시설명": "객실 31개"
  },
  {
    "상세시설ID": 617,
    "상세시설명": "체육관(다목적실)"
  },
  {
    "상세시설ID": 618,
    "상세시설명": "2동 116호"
  },
  {
    "상세시설ID": 619,
    "상세시설명": "334동 1층"
  },
  {
    "상세시설ID": 620,
    "상세시설명": "객실 18개"
  },
  {
    "상세시설ID": 621,
    "상세시설명": "농구장"
  },
  {
    "상세시설ID": 622,
    "상세시설명": "호텔"
  },
  {
    "상세시설ID": 623,
    "상세시설명": "762동 1층"
  },
  {
    "상세시설ID": 624,
    "상세시설명": "1111동 1층"
  },
  {
    "상세시설ID": 625,
    "상세시설명": "경로당 1층"
  },
  {
    "상세시설ID": 626,
    "상세시설명": "숙박동"
  },
  {
    "상세시설ID": 627,
    "상세시설명": "2216동 1층"
  },
  {
    "상세시설ID": 628,
    "상세시설명": "아이스 아레나"
  },
  {
    "상세시설ID": 629,
    "상세시설명": "다목적실, 예절실"
  },
  {
    "상세시설ID": 630,
    "상세시설명": "문화센터"
  },
  {
    "상세시설ID": 631,
    "상세시설명": "체험연수센터 객실동"
  },
  {
    "상세시설ID": 632,
    "상세시설명": "2507동 1층"
  },
  {
    "상세시설ID": 633,
    "상세시설명": "2406동 1층"
  },
  {
    "상세시설ID": 634,
    "상세시설명": "본관전체"
  },
  {
    "상세시설ID": 635,
    "상세시설명": "본관1층 지하"
  },
  {
    "상세시설ID": 636,
    "상세시설명": "본관 2층 강당"
  },
  {
    "상세시설ID": 637,
    "상세시설명": "다목적실(봉래관)"
  },
  {
    "상세시설ID": 638,
    "상세시설명": "강당(웅비관)"
  },
  {
    "상세시설ID": 639,
    "상세시설명": "정보센터동 4층 강당"
  },
  {
    "상세시설ID": 640,
    "상세시설명": "건지관"
  },
  {
    "상세시설ID": 641,
    "상세시설명": "지하강당"
  },
  {
    "상세시설ID": 642,
    "상세시설명": "경로당(204동)"
  },
  {
    "상세시설ID": 643,
    "상세시설명": "경로당(1902동)"
  },
  {
    "상세시설ID": 644,
    "상세시설명": "별동 체육관"
  },
  {
    "상세시설ID": 645,
    "상세시설명": "경로당(906동)"
  },
  {
    "상세시설ID": 646,
    "상세시설명": "라동 체육관"
  },
  {
    "상세시설ID": 647,
    "상세시설명": "목마홀(6층)"
  },
  {
    "상세시설ID": 648,
    "상세시설명": "107동 1층"
  },
  {
    "상세시설ID": 649,
    "상세시설명": "108동 1층"
  },
  {
    "상세시설ID": 650,
    "상세시설명": "교사동 1층 강당"
  },
  {
    "상세시설ID": 651,
    "상세시설명": "복합정보센터 내 강당"
  },
  {
    "상세시설ID": 652,
    "상세시설명": "교사시설(2층)"
  },
  {
    "상세시설ID": 653,
    "상세시설명": "다목적홀(4층)"
  },
  {
    "상세시설ID": 654,
    "상세시설명": "경로당 1~2층"
  },
  {
    "상세시설ID": 655,
    "상세시설명": "체육관 겸 정보화관(2층)"
  },
  {
    "상세시설ID": 656,
    "상세시설명": "가동 강당"
  },
  {
    "상세시설ID": 657,
    "상세시설명": "삼성현관"
  },
  {
    "상세시설ID": 658,
    "상세시설명": "4층(24실)"
  },
  {
    "상세시설ID": 659,
    "상세시설명": "6층(32실)"
  },
  {
    "상세시설ID": 660,
    "상세시설명": "체육관 및 강당"
  },
  {
    "상세시설ID": 661,
    "상세시설명": "다목정강당(나래관)"
  },
  {
    "상세시설ID": 662,
    "상세시설명": "본관 1층, 2층"
  },
  {
    "상세시설ID": 663,
    "상세시설명": "청운관 2층 강당"
  },
  {
    "상세시설ID": 664,
    "상세시설명": "2~8층"
  },
  {
    "상세시설ID": 665,
    "상세시설명": "노인복지회관"
  },
  {
    "상세시설ID": 666,
    "상세시설명": "신관 3층 강당"
  },
  {
    "상세시설ID": 667,
    "상세시설명": "선수합숙소"
  },
  {
    "상세시설ID": 668,
    "상세시설명": "생활체육관"
  },
  {
    "상세시설ID": 669,
    "상세시설명": "생활실"
  },
  {
    "상세시설ID": 670,
    "상세시설명": "동사무소"
  },
  {
    "상세시설ID": 671,
    "상세시설명": "한아름초등학교 체육관"
  },
  {
    "상세시설ID": 672,
    "상세시설명": "예배당"
  },
  {
    "상세시설ID": 673,
    "상세시설명": "종합교육관"
  },
  {
    "상세시설ID": 674,
    "상세시설명": "본관 4층"
  },
  {
    "상세시설ID": 675,
    "상세시설명": "강당,다목적실"
  },
  {
    "상세시설ID": 676,
    "상세시설명": "예배실"
  },
  {
    "상세시설ID": 677,
    "상세시설명": "2,3층"
  },
  {
    "상세시설ID": 678,
    "상세시설명": "요양원"
  },
  {
    "상세시설ID": 679,
    "상세시설명": "본관(2층)"
  },
  {
    "상세시설ID": 680,
    "상세시설명": "학교"
  },
  {
    "상세시설ID": 681,
    "상세시설명": "복지회관"
  },
  {
    "상세시설ID": 682,
    "상세시설명": "강당1층"
  },
  {
    "상세시설ID": 683,
    "상세시설명": "채육관"
  },
  {
    "상세시설ID": 684,
    "상세시설명": "급식소동"
  },
  {
    "상세시설ID": 685,
    "상세시설명": "강당 및 급식실"
  },
  {
    "상세시설ID": 686,
    "상세시설명": "급식실동 및 기숙사동"
  },
  {
    "상세시설ID": 687,
    "상세시설명": "건강센터"
  },
  {
    "상세시설ID": 688,
    "상세시설명": "교육지원청 wee센터"
  },
  {
    "상세시설ID": 689,
    "상세시설명": "본관(1동) 및 유치원동"
  },
  {
    "상세시설ID": 690,
    "상세시설명": "강당동 2층"
  },
  {
    "상세시설ID": 691,
    "상세시설명": "강당(인의관)"
  },
  {
    "상세시설ID": 692,
    "상세시설명": "문화예술회관"
  },
  {
    "상세시설ID": 693,
    "상세시설명": "창의예술동"
  },
  {
    "상세시설ID": 694,
    "상세시설명": "회진초등학교 본관동"
  },
  {
    "상세시설ID": 695,
    "상세시설명": "다목적"
  },
  {
    "상세시설ID": 696,
    "상세시설명": "2층(여) 및 3층(남)"
  },
  {
    "상세시설ID": 697,
    "상세시설명": "남악주민다목적생활체육관"
  },
  {
    "상세시설ID": 698,
    "상세시설명": "다목적강당(삼향관)"
  },
  {
    "상세시설ID": 699,
    "상세시설명": "체육관(하림관)"
  },
  {
    "상세시설ID": 700,
    "상세시설명": "강당(몽성관)"
  },
  {
    "상세시설ID": 701,
    "상세시설명": "무안생태갯벌과학관"
  },
  {
    "상세시설ID": 702,
    "상세시설명": "다목적강당(영성관)"
  },
  {
    "상세시설ID": 703,
    "상세시설명": "함양국민체육센터"
  },
  {
    "상세시설ID": 704,
    "상세시설명": "서면종합복지회관(2층)"
  },
  {
    "상세시설ID": 705,
    "상세시설명": "본관 2층"
  },
  {
    "상세시설ID": 706,
    "상세시설명": "운림1리마을회관"
  },
  {
    "상세시설ID": 707,
    "상세시설명": "지곡면사무소 대회의실"
  },
  {
    "상세시설ID": 708,
    "상세시설명": "함양군기관단체청사"
  },
  {
    "상세시설ID": 709,
    "상세시설명": "함양 종합사회복지관"
  },
  {
    "상세시설ID": 710,
    "상세시설명": "함양 문화예술회관"
  },
  {
    "상세시설ID": 711,
    "상세시설명": "3층 건물, 다목적실"
  },
  {
    "상세시설ID": 712,
    "상세시설명": "2층대회의실"
  },
  {
    "상세시설ID": 713,
    "상세시설명": "교사동, 체육관, 기숙사"
  },
  {
    "상세시설ID": 714,
    "상세시설명": "후관동 2층 다목적실"
  },
  {
    "상세시설ID": 715,
    "상세시설명": "객실 25"
  },
  {
    "상세시설ID": 716,
    "상세시설명": "체육관H동"
  },
  {
    "상세시설ID": 717,
    "상세시설명": "e편한세상 광주역 4단지 경로당"
  },
  {
    "상세시설ID": 718,
    "상세시설명": "강당, 체육관"
  },
  {
    "상세시설ID": 719,
    "상세시설명": "다목적 체육관"
  },
  {
    "상세시설ID": 720,
    "상세시설명": "대광로제비앙(아)경로당"
  },
  {
    "상세시설ID": 721,
    "상세시설명": "쌍령서희스타힐스 경로당"
  },
  {
    "상세시설ID": 722,
    "상세시설명": "경기도차오름터학생수영장"
  },
  {
    "상세시설ID": 723,
    "상세시설명": "강당, 체육관(지혜관)"
  },
  {
    "상세시설ID": 724,
    "상세시설명": "체육관 (2층)"
  },
  {
    "상세시설ID": 725,
    "상세시설명": "학습실"
  },
  {
    "상세시설ID": 726,
    "상세시설명": "송산초등학교 체육관"
  },
  {
    "상세시설ID": 727,
    "상세시설명": "병실"
  },
  {
    "상세시설ID": 728,
    "상세시설명": "소규모체육관"
  },
  {
    "상세시설ID": 729,
    "상세시설명": "다목적교실 및 태권도훈련장"
  },
  {
    "상세시설ID": 730,
    "상세시설명": "다목적실, 체육관"
  },
  {
    "상세시설ID": 731,
    "상세시설명": "펜싱연습장"
  },
  {
    "상세시설ID": 732,
    "상세시설명": "수성구청소년수련원"
  },
  {
    "상세시설ID": 733,
    "상세시설명": "주민센터"
  },
  {
    "상세시설ID": 734,
    "상세시설명": "대건학사기숙사동"
  },
  {
    "상세시설ID": 735,
    "상세시설명": "기숙사동"
  },
  {
    "상세시설ID": 736,
    "상세시설명": "강당체육관"
  },
  {
    "상세시설ID": 737,
    "상세시설명": "강당, 교사D동"
  },
  {
    "상세시설ID": 738,
    "상세시설명": "베네치아 모텔"
  },
  {
    "상세시설ID": 739,
    "상세시설명": "종교시설"
  },
  {
    "상세시설ID": 740,
    "상세시설명": "체력단련장"
  },
  {
    "상세시설ID": 741,
    "상세시설명": "본관, 강당"
  },
  {
    "상세시설ID": 742,
    "상세시설명": "급식소 및 다목적교실"
  },
  {
    "상세시설ID": 743,
    "상세시설명": "숭문관"
  },
  {
    "상세시설ID": 744,
    "상세시설명": "전일관"
  },
  {
    "상세시설ID": 745,
    "상세시설명": "급식소및다목적교실"
  },
  {
    "상세시설ID": 746,
    "상세시설명": "다목적교실 및 급식소"
  },
  {
    "상세시설ID": 747,
    "상세시설명": "종합학습실"
  },
  {
    "상세시설ID": 748,
    "상세시설명": "수성국민체육센터"
  },
  {
    "상세시설ID": 749,
    "상세시설명": "강당동-한솔관"
  },
  {
    "상세시설ID": 750,
    "상세시설명": "급식소 및 다목적강당"
  },
  {
    "상세시설ID": 751,
    "상세시설명": "특별교실동"
  },
  {
    "상세시설ID": 752,
    "상세시설명": "교사"
  },
  {
    "상세시설ID": 753,
    "상세시설명": "호텔(로비,식당,예식장)"
  },
  {
    "상세시설ID": 754,
    "상세시설명": "다목적실(재능관)"
  },
  {
    "상세시설ID": 755,
    "상세시설명": "본관(A동 교사동)"
  },
  {
    "상세시설ID": 756,
    "상세시설명": "본동"
  },
  {
    "상세시설ID": 757,
    "상세시설명": "강당, 교사시설 등"
  },
  {
    "상세시설ID": 758,
    "상세시설명": "본관동 객실"
  },
  {
    "상세시설ID": 759,
    "상세시설명": "노인복지시설(경로당)"
  },
  {
    "상세시설ID": 760,
    "상세시설명": "교사1동(나동,다동)"
  },
  {
    "상세시설ID": 761,
    "상세시설명": "1, 5층"
  },
  {
    "상세시설ID": 762,
    "상세시설명": "응급실"
  },
  {
    "상세시설ID": 763,
    "상세시설명": "기타"
  },
  {
    "상세시설ID": 764,
    "상세시설명": "본관 강당"
  },
  {
    "상세시설ID": 765,
    "상세시설명": "관공서/다목적실"
  },
  {
    "상세시설ID": 766,
    "상세시설명": "2층 다목적홀"
  },
  {
    "상세시설ID": 767,
    "상세시설명": "교사시설"
  },
  {
    "상세시설ID": 768,
    "상세시설명": "강당, 소강당"
  },
  {
    "상세시설ID": 769,
    "상세시설명": "급식실/다목적강당"
  },
  {
    "상세시설ID": 770,
    "상세시설명": "강당, 급식시설, 교사시설 등"
  },
  {
    "상세시설ID": 771,
    "상세시설명": "1층 다목적체육센터(대강당)"
  },
  {
    "상세시설ID": 772,
    "상세시설명": "1 체육관"
  },
  {
    "상세시설ID": 773,
    "상세시설명": "어울림행복누리터 본관"
  },
  {
    "상세시설ID": 774,
    "상세시설명": "과일나라테마공원학습관"
  },
  {
    "상세시설ID": 775,
    "상세시설명": "본관 5층 체육관"
  },
  {
    "상세시설ID": 776,
    "상세시설명": "강당(본관동 2층)"
  },
  {
    "상세시설ID": 777,
    "상세시설명": "교사1~3호동/강당(3층)"
  },
  {
    "상세시설ID": 778,
    "상세시설명": "교사1~3호동/강당(2층)"
  },
  {
    "상세시설ID": 779,
    "상세시설명": "교사동,본관동,특별교실동,강당(2층)"
  },
  {
    "상세시설ID": 780,
    "상세시설명": "다목적강당(F동 2층)"
  },
  {
    "상세시설ID": 781,
    "상세시설명": "강당(신관 5층)"
  },
  {
    "상세시설ID": 782,
    "상세시설명": "교사1~2동,강당(3동 2층)"
  },
  {
    "상세시설ID": 783,
    "상세시설명": "강당(4동 2층)"
  },
  {
    "상세시설ID": 784,
    "상세시설명": "용유초 교사동"
  },
  {
    "상세시설ID": 785,
    "상세시설명": "다목적 체육관(3층)"
  },
  {
    "상세시설ID": 786,
    "상세시설명": "체육관(지하 2층)"
  },
  {
    "상세시설ID": 787,
    "상세시설명": "교실, 강당"
  },
  {
    "상세시설ID": 788,
    "상세시설명": "교실, 체육관, 강당"
  },
  {
    "상세시설ID": 789,
    "상세시설명": "교실,급식소"
  },
  {
    "상세시설ID": 790,
    "상세시설명": "양천디지털미디어센터"
  },
  {
    "상세시설ID": 791,
    "상세시설명": "1층 전시실"
  },
  {
    "상세시설ID": 792,
    "상세시설명": "교사동(체육관)"
  },
  {
    "상세시설ID": 793,
    "상세시설명": "교사1동(신관)(3층)"
  },
  {
    "상세시설ID": 794,
    "상세시설명": "체육관 및 급식실"
  },
  {
    "상세시설ID": 795,
    "상세시설명": "교사2동(3층)"
  },
  {
    "상세시설ID": 796,
    "상세시설명": "강당 겸 체육관(2층)"
  },
  {
    "상세시설ID": 797,
    "상세시설명": "후관(BTL)-교사동(체육관1층)"
  },
  {
    "상세시설ID": 798,
    "상세시설명": "정보관(체육관)(2층)"
  },
  {
    "상세시설ID": 799,
    "상세시설명": "체육관 겸 다목적강당(3층)"
  },
  {
    "상세시설ID": 800,
    "상세시설명": "다목적 강당(2층)"
  },
  {
    "상세시설ID": 801,
    "상세시설명": "체육관2층"
  },
  {
    "상세시설ID": 802,
    "상세시설명": "불광관(다목적강당)"
  },
  {
    "상세시설ID": 803,
    "상세시설명": "성전"
  },
  {
    "상세시설ID": 804,
    "상세시설명": "신관4층체육관"
  },
  {
    "상세시설ID": 805,
    "상세시설명": "1층 유치원 3교실"
  },
  {
    "상세시설ID": 806,
    "상세시설명": "수락관"
  },
  {
    "상세시설ID": 807,
    "상세시설명": "다목적체육관 3층"
  },
  {
    "상세시설ID": 808,
    "상세시설명": "4층 대강당 및 경로식당"
  },
  {
    "상세시설ID": 809,
    "상세시설명": "별관 2층 체육관"
  },
  {
    "상세시설ID": 810,
    "상세시설명": "금곡실내체육관"
  },
  {
    "상세시설ID": 811,
    "상세시설명": "본관동 식당 2층"
  },
  {
    "상세시설ID": 812,
    "상세시설명": "강의실1,2"
  },
  {
    "상세시설ID": 813,
    "상세시설명": "100년 상상관"
  },
  {
    "상세시설ID": 814,
    "상세시설명": "종합운동장"
  },
  {
    "상세시설ID": 815,
    "상세시설명": "소체육실"
  },
  {
    "상세시설ID": 816,
    "상세시설명": "음악당"
  },
  {
    "상세시설ID": 817,
    "상세시설명": "교사1동 체육관"
  },
  {
    "상세시설ID": 818,
    "상세시설명": "본관 1, 2, 3, 4층"
  },
  {
    "상세시설ID": 819,
    "상세시설명": "물향기센터 2층 체육관"
  },
  {
    "상세시설ID": 820,
    "상세시설명": "스포츠센터 2층 다목적강당"
  },
  {
    "상세시설ID": 821,
    "상세시설명": "1층로비, 4층 강당, 지하 체력단련실"
  },
  {
    "상세시설ID": 822,
    "상세시설명": "본관2층 체육관"
  },
  {
    "상세시설ID": 823,
    "상세시설명": "교사동 체육관(늘푸른희망관)"
  },
  {
    "상세시설ID": 824,
    "상세시설명": "교사동 3층 체육관"
  },
  {
    "상세시설ID": 825,
    "상세시설명": "교사동 체육관"
  },
  {
    "상세시설ID": 826,
    "상세시설명": "본관3층 다목적강당"
  },
  {
    "상세시설ID": 827,
    "상세시설명": "키움관 2층 체육관"
  },
  {
    "상세시설ID": 828,
    "상세시설명": "체육관(주차장건물2층빛가람관)"
  },
  {
    "상세시설ID": 829,
    "상세시설명": "3층 자유관 체육관"
  },
  {
    "상세시설ID": 830,
    "상세시설명": "교사동 2층 다목적강당"
  },
  {
    "상세시설ID": 831,
    "상세시설명": "강당(1층)"
  },
  {
    "상세시설ID": 832,
    "상세시설명": "대회의실(5층)"
  },
  {
    "상세시설ID": 833,
    "상세시설명": "대강당(1층)/다목적실(2층)/공연장(3층)"
  },
  {
    "상세시설ID": 834,
    "상세시설명": "다목적체육관(2층)"
  },
  {
    "상세시설ID": 835,
    "상세시설명": "다목적실(3층)/회의실(!층)"
  },
  {
    "상세시설ID": 836,
    "상세시설명": "교사동2 2층강당"
  },
  {
    "상세시설ID": 837,
    "상세시설명": "체육관동 다목적체육관"
  },
  {
    "상세시설ID": 838,
    "상세시설명": "교사나동 축구부생활관 1,2,3층"
  },
  {
    "상세시설ID": 839,
    "상세시설명": "1층 급식실"
  },
  {
    "상세시설ID": 840,
    "상세시설명": "지하1층 다목적실"
  },
  {
    "상세시설ID": 841,
    "상세시설명": "1층 별관 체육관"
  },
  {
    "상세시설ID": 842,
    "상세시설명": "교사동 3층 다목적강당(체육관)"
  },
  {
    "상세시설ID": 843,
    "상세시설명": "2층꿈나래관(체육관)"
  },
  {
    "상세시설ID": 844,
    "상세시설명": "1동 2층 실내체육관"
  },
  {
    "상세시설ID": 845,
    "상세시설명": "교사동 은빛누리관 2층 체육관"
  },
  {
    "상세시설ID": 846,
    "상세시설명": "교사동 2층 어울관(체육관)"
  },
  {
    "상세시설ID": 847,
    "상세시설명": "교사동 3층 다목적강당"
  },
  {
    "상세시설ID": 848,
    "상세시설명": "덕풍3동 행정복지센터 3층다목적실"
  },
  {
    "상세시설ID": 849,
    "상세시설명": "본관3층 체육관"
  },
  {
    "상세시설ID": 850,
    "상세시설명": "감일동행정복지센터6층"
  },
  {
    "상세시설ID": 851,
    "상세시설명": "4층 다목적실, 5층 체육관(삼색관), 5층"
  },
  {
    "상세시설ID": 852,
    "상세시설명": "교사2동 1층 체육관"
  },
  {
    "상세시설ID": 853,
    "상세시설명": "본관동 3층 다목적강당"
  },
  {
    "상세시설ID": 854,
    "상세시설명": "1동 2층 다목적강당"
  },
  {
    "상세시설ID": 855,
    "상세시설명": "고림1·10통 경로당"
  },
  {
    "상세시설ID": 856,
    "상세시설명": "소회의실(지하1층)"
  },
  {
    "상세시설ID": 857,
    "상세시설명": "고림4통 경로당"
  },
  {
    "상세시설ID": 858,
    "상세시설명": "5층 다목적실"
  },
  {
    "상세시설ID": 859,
    "상세시설명": "한강골드호텔"
  },
  {
    "상세시설ID": 860,
    "상세시설명": "창조관 대강당"
  },
  {
    "상세시설ID": 861,
    "상세시설명": "구일관 체육관"
  },
  {
    "상세시설ID": 862,
    "상세시설명": "경로당(1~3층)"
  },
  {
    "상세시설ID": 863,
    "상세시설명": "체육관(교사동 3층)"
  },
  {
    "상세시설ID": 864,
    "상세시설명": "다목적강당(체육관동 3F)"
  },
  {
    "상세시설ID": 865,
    "상세시설명": "롯데시티호텔"
  },
  {
    "상세시설ID": 866,
    "상세시설명": "제이에스호스텔"
  },
  {
    "상세시설ID": 867,
    "상세시설명": "고산마루"
  },
  {
    "상세시설ID": 868,
    "상세시설명": "대체육관, 다목적실 유도장"
  },
  {
    "상세시설ID": 869,
    "상세시설명": "신관4층 체육관"
  },
  {
    "상세시설ID": 870,
    "상세시설명": "대체육관"
  },
  {
    "상세시설ID": 871,
    "상세시설명": "후관 4층 다목적실"
  },
  {
    "상세시설ID": 872,
    "상세시설명": "동관 2층 강당"
  },
  {
    "상세시설ID": 873,
    "상세시설명": "꿈마루 1층 체육관"
  },
  {
    "상세시설ID": 874,
    "상세시설명": "4층 나곡홀"
  },
  {
    "상세시설ID": 875,
    "상세시설명": "강당(다목적실)"
  },
  {
    "상세시설ID": 876,
    "상세시설명": "관리동 지하2층 경로당"
  },
  {
    "상세시설ID": 877,
    "상세시설명": "관리동 1층 경로당"
  },
  {
    "상세시설ID": 878,
    "상세시설명": "3층 서그내 강당"
  },
  {
    "상세시설ID": 879,
    "상세시설명": "2층 체육관(강당)"
  },
  {
    "상세시설ID": 880,
    "상세시설명": "1층 다목적강당"
  },
  {
    "상세시설ID": 881,
    "상세시설명": "1층 청민실"
  },
  {
    "상세시설ID": 882,
    "상세시설명": "체육동"
  },
  {
    "상세시설ID": 883,
    "상세시설명": "5층 동백관"
  },
  {
    "상세시설ID": 884,
    "상세시설명": "체육관(본관3F)"
  },
  {
    "상세시설ID": 885,
    "상세시설명": "특별교실동(늘솔채)2층"
  },
  {
    "상세시설ID": 886,
    "상세시설명": "회의실(4층)"
  },
  {
    "상세시설ID": 887,
    "상세시설명": "경로당(1층)"
  },
  {
    "상세시설ID": 888,
    "상세시설명": "대체육관(5층)"
  },
  {
    "상세시설ID": 889,
    "상세시설명": "다목적강당(본관동 2층)"
  },
  {
    "상세시설ID": 890,
    "상세시설명": "다목적강당(다목적강당동)"
  },
  {
    "상세시설ID": 891,
    "상세시설명": "경로당(2층)"
  },
  {
    "상세시설ID": 892,
    "상세시설명": "체육관(체육관동 1층)"
  },
  {
    "상세시설ID": 893,
    "상세시설명": "체육관(정보화동 3층)"
  },
  {
    "상세시설ID": 894,
    "상세시설명": "체육관(본관동4층)"
  },
  {
    "상세시설ID": 895,
    "상세시설명": "다목적강당(3F)"
  },
  {
    "상세시설ID": 896,
    "상세시설명": "브릿지호텔(유동적)"
  },
  {
    "상세시설ID": 897,
    "상세시설명": "체육관(우신관 2층)"
  },
  {
    "상세시설ID": 898,
    "상세시설명": "다목적회의실(2층)"
  },
  {
    "상세시설ID": 899,
    "상세시설명": "어울림실(교사동 1층)"
  },
  {
    "상세시설ID": 900,
    "상세시설명": "대체육관 (3층)"
  },
  {
    "상세시설ID": 901,
    "상세시설명": "나사렛실(지하1층), 유아실(2층)"
  },
  {
    "상세시설ID": 902,
    "상세시설명": "급식실(늘새롬관 2~3층)"
  },
  {
    "상세시설ID": 903,
    "상세시설명": "강당동(본관3층)"
  },
  {
    "상세시설ID": 904,
    "상세시설명": "경로당(2~3층)"
  },
  {
    "상세시설ID": 905,
    "상세시설명": "체육관(정보동 4층)"
  },
  {
    "상세시설ID": 906,
    "상세시설명": "체육관(강당동 2층)"
  },
  {
    "상세시설ID": 907,
    "상세시설명": "다목적강당(강당동 3층)"
  },
  {
    "상세시설ID": 908,
    "상세시설명": "다목적실,휴게실(지하1층)"
  },
  {
    "상세시설ID": 909,
    "상세시설명": "다목적체육관(비전센터6층)"
  },
  {
    "상세시설ID": 910,
    "상세시설명": "다목적강당(본관동4층)"
  },
  {
    "상세시설ID": 911,
    "상세시설명": "다목적강당(체육관동 2층)"
  },
  {
    "상세시설ID": 912,
    "상세시설명": "소공연장(5F)"
  },
  {
    "상세시설ID": 913,
    "상세시설명": "하이서울유스호스텔(유동적)"
  },
  {
    "상세시설ID": 914,
    "상세시설명": "강당, 식당"
  },
  {
    "상세시설ID": 915,
    "상세시설명": "청룡관동(강당)"
  },
  {
    "상세시설ID": 916,
    "상세시설명": "소강당(교사동 지하2층)"
  },
  {
    "상세시설ID": 917,
    "상세시설명": "강당(2층, 4층)"
  },
  {
    "상세시설ID": 918,
    "상세시설명": "다목적 강당, 급식실"
  },
  {
    "상세시설ID": 919,
    "상세시설명": "교실, 체육관 등"
  },
  {
    "상세시설ID": 920,
    "상세시설명": "도서관,컴퓨터실,과학실"
  },
  {
    "상세시설ID": 921,
    "상세시설명": "다목적체육관(2층 강당)"
  },
  {
    "상세시설ID": 922,
    "상세시설명": "1층 소회의실"
  },
  {
    "상세시설ID": 923,
    "상세시설명": "지하1층 갤러리"
  },
  {
    "상세시설ID": 924,
    "상세시설명": "상현3동행정복지센터 회의실"
  },
  {
    "상세시설ID": 925,
    "상세시설명": "별관 체육관/1층"
  },
  {
    "상세시설ID": 926,
    "상세시설명": "체육관 2층 강당"
  },
  {
    "상세시설ID": 927,
    "상세시설명": "3층 성덕관"
  },
  {
    "상세시설ID": 928,
    "상세시설명": "5층 다목적실, 강당"
  },
  {
    "상세시설ID": 929,
    "상세시설명": "숙소 및 강당"
  },
  {
    "상세시설ID": 930,
    "상세시설명": "신둔실내체육관"
  },
  {
    "상세시설ID": 931,
    "상세시설명": "체육관, 교실, 강당"
  },
  {
    "상세시설ID": 932,
    "상세시설명": "한반도관(생활관)"
  },
  {
    "상세시설ID": 933,
    "상세시설명": "삼성관"
  },
  {
    "상세시설ID": 934,
    "상세시설명": "배트민턴장"
  },
  {
    "상세시설ID": 935,
    "상세시설명": "체험실"
  },
  {
    "상세시설ID": 936,
    "상세시설명": "주민자치센터"
  },
  {
    "상세시설ID": 937,
    "상세시설명": "2층 프로그램실"
  },
  {
    "상세시설ID": 938,
    "상세시설명": "1층 마을회관"
  },
  {
    "상세시설ID": 939,
    "상세시설명": "1층 다목적회의실"
  },
  {
    "상세시설ID": 940,
    "상세시설명": "급식실, 다목적실"
  },
  {
    "상세시설ID": 941,
    "상세시설명": "다목적 교실"
  },
  {
    "상세시설ID": 942,
    "상세시설명": "다목적 교실 및 급식소"
  },
  {
    "상세시설ID": 943,
    "상세시설명": "노인정"
  },
  {
    "상세시설ID": 944,
    "상세시설명": "산척면 행정경로당"
  },
  {
    "상세시설ID": 945,
    "상세시설명": "산척면 서곡경로당"
  },
  {
    "상세시설ID": 946,
    "상세시설명": "강의실(9개소), 객실(136개소)"
  },
  {
    "상세시설ID": 947,
    "상세시설명": "8층 강당"
  },
  {
    "상세시설ID": 948,
    "상세시설명": "진천중학교 다목적교실(체육관)"
  },
  {
    "상세시설ID": 949,
    "상세시설명": "초평초등학교 체육관"
  },
  {
    "상세시설ID": 950,
    "상세시설명": "구정초등학교 다목적교실"
  },
  {
    "상세시설ID": 951,
    "상세시설명": "문상초등학교 강당"
  },
  {
    "상세시설ID": 952,
    "상세시설명": "문백초등학교 강당"
  },
  {
    "상세시설ID": 953,
    "상세시설명": "이월중학교 다목적교실"
  },
  {
    "상세시설ID": 954,
    "상세시설명": "광혜원고등학교 본관"
  },
  {
    "상세시설ID": 955,
    "상세시설명": "광혜원고등학교 다목적교실"
  },
  {
    "상세시설ID": 956,
    "상세시설명": "만승초등학교 본관"
  },
  {
    "상세시설ID": 957,
    "상세시설명": "광혜원LH2단지경로당"
  },
  {
    "상세시설ID": 958,
    "상세시설명": "옥동초등학교 강당"
  },
  {
    "상세시설ID": 959,
    "상세시설명": "본관,체육관"
  },
  {
    "상세시설ID": 960,
    "상세시설명": "체육관(동녘관)"
  },
  {
    "상세시설ID": 961,
    "상세시설명": "게이트볼장"
  },
  {
    "상세시설ID": 962,
    "상세시설명": "상황실"
  },
  {
    "상세시설ID": 963,
    "상세시설명": "2층 세미나실"
  },
  {
    "상세시설ID": 964,
    "상세시설명": "감곡초등학교 본관, 후관 교실, 강당"
  },
  {
    "상세시설ID": 965,
    "상세시설명": "평곡2리마을회관"
  },
  {
    "상세시설ID": 966,
    "상세시설명": "한천초등학교 다목적교실"
  },
  {
    "상세시설ID": 967,
    "상세시설명": "음성문화예술회관 공연동 1층"
  },
  {
    "상세시설ID": 968,
    "상세시설명": "금왕보건지소 본관"
  },
  {
    "상세시설ID": 969,
    "상세시설명": "금왕읍행정복지센터(본관)"
  },
  {
    "상세시설ID": 970,
    "상세시설명": "프로그램실/ 건강증진실"
  },
  {
    "상세시설ID": 971,
    "상세시설명": "급식소 및 다목적 교실"
  },
  {
    "상세시설ID": 972,
    "상세시설명": "급식시설, 교사시설 등"
  },
  {
    "상세시설ID": 973,
    "상세시설명": "16동 목련관"
  },
  {
    "상세시설ID": 974,
    "상세시설명": "강당(G동)"
  },
  {
    "상세시설ID": 975,
    "상세시설명": "별관 체육관"
  },
  {
    "상세시설ID": 976,
    "상세시설명": "한벌2리경로당"
  },
  {
    "상세시설ID": 977,
    "상세시설명": "문암3리 경로당"
  },
  {
    "상세시설ID": 978,
    "상세시설명": "축구센터"
  },
  {
    "상세시설ID": 979,
    "상세시설명": "장승포라온호텔"
  },
  {
    "상세시설ID": 980,
    "상세시설명": "파우제호텔"
  },
  {
    "상세시설ID": 981,
    "상세시설명": "교사시설(본관)"
  },
  {
    "상세시설ID": 982,
    "상세시설명": "10인실 객실"
  },
  {
    "상세시설ID": 983,
    "상세시설명": "체육관(강당)"
  },
  {
    "상세시설ID": 984,
    "상세시설명": "강당(별동)"
  },
  {
    "상세시설ID": 985,
    "상세시설명": "금산고본관교사"
  },
  {
    "상세시설ID": 986,
    "상세시설명": "금산고급식실동"
  },
  {
    "상세시설ID": 987,
    "상세시설명": "교실,강당"
  },
  {
    "상세시설ID": 988,
    "상세시설명": "강당,교실"
  },
  {
    "상세시설ID": 989,
    "상세시설명": "금산동초본관교사"
  },
  {
    "상세시설ID": 990,
    "상세시설명": "교사1동"
  },
  {
    "상세시설ID": 991,
    "상세시설명": "체육관(한마음관)"
  },
  {
    "상세시설ID": 992,
    "상세시설명": "강당, 다목적실"
  },
  {
    "상세시설ID": 993,
    "상세시설명": "대회의 실 등"
  },
  {
    "상세시설ID": 994,
    "상세시설명": "서관동 3층 강당"
  },
  {
    "상세시설ID": 995,
    "상세시설명": "교육문화관 체육관"
  },
  {
    "상세시설ID": 996,
    "상세시설명": "주차장 2층"
  },
  {
    "상세시설ID": 997,
    "상세시설명": "별관 체육실 1층"
  },
  {
    "상세시설ID": 998,
    "상세시설명": "서관동 강당"
  },
  {
    "상세시설ID": 999,
    "상세시설명": "다목적실(본관)"
  },
  {
    "상세시설ID": 1000,
    "상세시설명": "급식/강당"
  },
  {
    "상세시설ID": 1001,
    "상세시설명": "강화여자중학교 본관"
  },
  {
    "상세시설ID": 1002,
    "상세시설명": "동광중학교 해오름관"
  },
  {
    "상세시설ID": 1003,
    "상세시설명": "2층 안심마을경로당,3층마을그늘터"
  },
  {
    "상세시설ID": 1004,
    "상세시설명": "지층, 2층"
  },
  {
    "상세시설ID": 1005,
    "상세시설명": "2층 소회의실, 3층 대강당"
  },
  {
    "상세시설ID": 1006,
    "상세시설명": "기숙사(2층, 6층)"
  },
  {
    "상세시설ID": 1007,
    "상세시설명": "28실"
  },
  {
    "상세시설ID": 1008,
    "상세시설명": "교사(별관동)"
  },
  {
    "상세시설ID": 1009,
    "상세시설명": "강당/체육관"
  },
  {
    "상세시설ID": 1010,
    "상세시설명": "2층-4층"
  },
  {
    "상세시설ID": 1011,
    "상세시설명": "본관 2층, 별관 2층"
  },
  {
    "상세시설ID": 1012,
    "상세시설명": "3층-4층"
  },
  {
    "상세시설ID": 1013,
    "상세시설명": "1층 대회의실, 2층"
  },
  {
    "상세시설ID": 1014,
    "상세시설명": "2층, 4층"
  },
  {
    "상세시설ID": 1015,
    "상세시설명": "3층 다목적 체육관"
  },
  {
    "상세시설ID": 1016,
    "상세시설명": "교사2호동 1층"
  },
  {
    "상세시설ID": 1017,
    "상세시설명": "급식시설동"
  },
  {
    "상세시설ID": 1018,
    "상세시설명": "1층 다목적 체육관"
  },
  {
    "상세시설ID": 1019,
    "상세시설명": "본관, 체육관"
  },
  {
    "상세시설ID": 1020,
    "상세시설명": "본관, 강당 등"
  },
  {
    "상세시설ID": 1021,
    "상세시설명": "본관, 체육관 등"
  },
  {
    "상세시설ID": 1022,
    "상세시설명": "본관2층"
  },
  {
    "상세시설ID": 1023,
    "상세시설명": "강당(4동)"
  },
  {
    "상세시설ID": 1024,
    "상세시설명": "본관 대회의실"
  },
  {
    "상세시설ID": 1025,
    "상세시설명": "교육관"
  },
  {
    "상세시설ID": 1026,
    "상세시설명": "대회의실(3층)"
  },
  {
    "상세시설ID": 1027,
    "상세시설명": "소규모강당"
  },
  {
    "상세시설ID": 1028,
    "상세시설명": "실습동 5층 다목적강당"
  },
  {
    "상세시설ID": 1029,
    "상세시설명": "10층(45실)"
  },
  {
    "상세시설ID": 1030,
    "상세시설명": "10층(40실)"
  },
  {
    "상세시설ID": 1031,
    "상세시설명": "대강의실"
  },
  {
    "상세시설ID": 1032,
    "상세시설명": "강당(별개)"
  },
  {
    "상세시설ID": 1033,
    "상세시설명": "본관 내 강당"
  },
  {
    "상세시설ID": 1034,
    "상세시설명": "본관 지하1층"
  },
  {
    "상세시설ID": 1035,
    "상세시설명": "본관1층"
  },
  {
    "상세시설ID": 1036,
    "상세시설명": "본관 다목적강당(3층)"
  },
  {
    "상세시설ID": 1037,
    "상세시설명": "유치원동"
  },
  {
    "상세시설ID": 1038,
    "상세시설명": "강당(천봉관)"
  },
  {
    "상세시설ID": 1039,
    "상세시설명": "B동(강당동)"
  },
  {
    "상세시설ID": 1040,
    "상세시설명": "급식소, 다목적강당"
  },
  {
    "상세시설ID": 1041,
    "상세시설명": "기타시설"
  },
  {
    "상세시설ID": 1042,
    "상세시설명": "본관3층 대강당"
  },
  {
    "상세시설ID": 1043,
    "상세시설명": "본관동(1, 2층)"
  },
  {
    "상세시설ID": 1044,
    "상세시설명": "강당(석암홀)"
  },
  {
    "상세시설ID": 1045,
    "상세시설명": "급식소, 강당동"
  },
  {
    "상세시설ID": 1046,
    "상세시설명": "육상보조경기장 및 트레이닝시설"
  },
  {
    "상세시설ID": 1047,
    "상세시설명": "숲속의집"
  },
  {
    "상세시설ID": 1048,
    "상세시설명": "교사2동"
  },
  {
    "상세시설ID": 1049,
    "상세시설명": "후관동(3층 강당)"
  },
  {
    "상세시설ID": 1050,
    "상세시설명": "본관동(4층)"
  },
  {
    "상세시설ID": 1051,
    "상세시설명": "본관동(지상2층체육관)"
  },
  {
    "상세시설ID": 1052,
    "상세시설명": "A동"
  },
  {
    "상세시설ID": 1053,
    "상세시설명": "다목적실(별관)"
  },
  {
    "상세시설ID": 1054,
    "상세시설명": "다목적강당(체육관)"
  },
  {
    "상세시설ID": 1055,
    "상세시설명": "사택(교사동)"
  },
  {
    "상세시설ID": 1056,
    "상세시설명": "실내 테니스장"
  },
  {
    "상세시설ID": 1057,
    "상세시설명": "1층 복합체육관"
  },
  {
    "상세시설ID": 1058,
    "상세시설명": "2층 대체육관"
  },
  {
    "상세시설ID": 1059,
    "상세시설명": "대체육관 3층"
  },
  {
    "상세시설ID": 1060,
    "상세시설명": "관청5리 다목적회관"
  },
  {
    "상세시설ID": 1061,
    "상세시설명": "4,5층"
  },
  {
    "상세시설ID": 1062,
    "상세시설명": "3층 다목적체육관"
  },
  {
    "상세시설ID": 1063,
    "상세시설명": ""
  },
  {
    "상세시설ID": 1064,
    "상세시설명": "특수학급동"
  },
  {
    "상세시설ID": 1065,
    "상세시설명": "식당, 체육관 등"
  },
  {
    "상세시설ID": 1066,
    "상세시설명": "다모임관(강당)"
  },
  {
    "상세시설ID": 1067,
    "상세시설명": "한빛관"
  },
  {
    "상세시설ID": 1068,
    "상세시설명": "과학동"
  },
  {
    "상세시설ID": 1069,
    "상세시설명": "부산진구국민체육센터"
  },
  {
    "상세시설ID": 1070,
    "상세시설명": "솔빛관강당"
  },
  {
    "상세시설ID": 1071,
    "상세시설명": "효봉관,선화관"
  },
  {
    "상세시설ID": 1072,
    "상세시설명": "교사동 1층"
  },
  {
    "상세시설ID": 1073,
    "상세시설명": "1층 대체육관"
  },
  {
    "상세시설ID": 1074,
    "상세시설명": "다목적실 1층"
  },
  {
    "상세시설ID": 1075,
    "상세시설명": "다목적관"
  },
  {
    "상세시설ID": 1076,
    "상세시설명": "체육관(신동교육문화회관)"
  },
  {
    "상세시설ID": 1077,
    "상세시설명": "공연장"
  },
  {
    "상세시설ID": 1078,
    "상세시설명": "다목적실(미술실)"
  },
  {
    "상세시설ID": 1079,
    "상세시설명": "반포4동주민센터"
  },
  {
    "상세시설ID": 1080,
    "상세시설명": "미성관"
  },
  {
    "상세시설ID": 1081,
    "상세시설명": "소흘국민체육센터"
  },
  {
    "상세시설ID": 1082,
    "상세시설명": "본관동(강당)"
  },
  {
    "상세시설ID": 1083,
    "상세시설명": "양재1동주민센터"
  },
  {
    "상세시설ID": 1084,
    "상세시설명": "지축관,예체능관"
  },
  {
    "상세시설ID": 1085,
    "상세시설명": "집단프로그램실"
  },
  {
    "상세시설ID": 1086,
    "상세시설명": "강당,식당"
  },
  {
    "상세시설ID": 1087,
    "상세시설명": "체육관,교실"
  },
  {
    "상세시설ID": 1088,
    "상세시설명": "지하 유희실"
  },
  {
    "상세시설ID": 1089,
    "상세시설명": "본관대강당"
  },
  {
    "상세시설ID": 1090,
    "상세시설명": "한빛관 2층 강당"
  },
  {
    "상세시설ID": 1091,
    "상세시설명": "4층 이벤트홀"
  },
  {
    "상세시설ID": 1092,
    "상세시설명": "6층 대회의실"
  },
  {
    "상세시설ID": 1093,
    "상세시설명": "7층 회의실"
  },
  {
    "상세시설ID": 1094,
    "상세시설명": "교실24, 체육관1"
  },
  {
    "상세시설ID": 1095,
    "상세시설명": "급식실1, 체육관1, 교실64"
  },
  {
    "상세시설ID": 1096,
    "상세시설명": "교실42, 강당1"
  },
  {
    "상세시설ID": 1097,
    "상세시설명": "강당1"
  },
  {
    "상세시설ID": 1098,
    "상세시설명": "교실45, 강당1"
  },
  {
    "상세시설ID": 1099,
    "상세시설명": "지하층"
  },
  {
    "상세시설ID": 1100,
    "상세시설명": "양재2동주민센터"
  },
  {
    "상세시설ID": 1101,
    "상세시설명": "오라카이 청계산 호텔"
  },
  {
    "상세시설ID": 1102,
    "상세시설명": "회의실, 체육관"
  },
  {
    "상세시설ID": 1103,
    "상세시설명": "체육교실(5층)"
  },
  {
    "상세시설ID": 1104,
    "상세시설명": "교육문화회관(체육관)"
  },
  {
    "상세시설ID": 1105,
    "상세시설명": "강당동(체육관)"
  },
  {
    "상세시설ID": 1106,
    "상세시설명": "삼성재"
  },
  {
    "상세시설ID": 1107,
    "상세시설명": "생활체육교실"
  },
  {
    "상세시설ID": 1108,
    "상세시설명": "체육교실"
  },
  {
    "상세시설ID": 1109,
    "상세시설명": "체육관 (해오름관3층)"
  },
  {
    "상세시설ID": 1110,
    "상세시설명": "다목적 강당 등"
  },
  {
    "상세시설ID": 1111,
    "상세시설명": "체육관, 교실"
  },
  {
    "상세시설ID": 1112,
    "상세시설명": "교사동, 다목적강당"
  },
  {
    "상세시설ID": 1113,
    "상세시설명": "G동"
  },
  {
    "상세시설ID": 1114,
    "상세시설명": "체육관, 급식실"
  },
  {
    "상세시설ID": 1115,
    "상세시설명": "본관(4층 예절실)"
  },
  {
    "상세시설ID": 1116,
    "상세시설명": "5층 다목적강당"
  },
  {
    "상세시설ID": 1117,
    "상세시설명": "본관(교사동)"
  },
  {
    "상세시설ID": 1118,
    "상세시설명": "교사신관동(강당)"
  },
  {
    "상세시설ID": 1119,
    "상세시설명": "한마음관(강당)"
  },
  {
    "상세시설ID": 1120,
    "상세시설명": "대진생활관(체육관)"
  },
  {
    "상세시설ID": 1121,
    "상세시설명": "백주념기념관(체육관)"
  },
  {
    "상세시설ID": 1122,
    "상세시설명": "체육관(4층)"
  },
  {
    "상세시설ID": 1123,
    "상세시설명": "용추관"
  },
  {
    "상세시설ID": 1124,
    "상세시설명": "교실51, 강당1"
  },
  {
    "상세시설ID": 1125,
    "상세시설명": "다목적강당, 급식실"
  },
  {
    "상세시설ID": 1126,
    "상세시설명": "1층 찜질방"
  },
  {
    "상세시설ID": 1127,
    "상세시설명": "1층 실내체육관"
  },
  {
    "상세시설ID": 1128,
    "상세시설명": "1층 및 3층 강당"
  },
  {
    "상세시설ID": 1129,
    "상세시설명": "1층 아동자료실 및 휴게실"
  },
  {
    "상세시설ID": 1130,
    "상세시설명": "1층 희망극장"
  },
  {
    "상세시설ID": 1131,
    "상세시설명": "2~3층"
  },
  {
    "상세시설ID": 1132,
    "상세시설명": "일동체육문화센터"
  },
  {
    "상세시설ID": 1133,
    "상세시설명": "시립소흘도서관"
  },
  {
    "상세시설ID": 1134,
    "상세시설명": "1~2층"
  },
  {
    "상세시설ID": 1135,
    "상세시설명": "3병동"
  },
  {
    "상세시설ID": 1136,
    "상세시설명": "보훈회관"
  },
  {
    "상세시설ID": 1137,
    "상세시설명": "교실 등"
  },
  {
    "상세시설ID": 1138,
    "상세시설명": "금구초등학교 체육관"
  },
  {
    "상세시설ID": 1139,
    "상세시설명": "고실초등학교 체육관"
  },
  {
    "상세시설ID": 1140,
    "상세시설명": "광주여자대학교 시립유니버시아드 체육관"
  },
  {
    "상세시설ID": 1141,
    "상세시설명": "세미나실"
  },
  {
    "상세시설ID": 1142,
    "상세시설명": "본관(5층 다목적 교실)"
  },
  {
    "상세시설ID": 1143,
    "상세시설명": "본관, 다목적 강당"
  },
  {
    "상세시설ID": 1144,
    "상세시설명": "강당 및 생활관"
  },
  {
    "상세시설ID": 1145,
    "상세시설명": "신관 4층 다목적홀"
  },
  {
    "상세시설ID": 1146,
    "상세시설명": "선운중학교 체육관"
  },
  {
    "상세시설ID": 1147,
    "상세시설명": "정광고등학교 체육관"
  },
  {
    "상세시설ID": 1148,
    "상세시설명": "어룡초등학교 체육관"
  },
  {
    "상세시설ID": 1149,
    "상세시설명": "4층 배드민턴장"
  },
  {
    "상세시설ID": 1150,
    "상세시설명": "첨단초등학교 체육관"
  },
  {
    "상세시설ID": 1151,
    "상세시설명": "첨단중학교 체육관"
  },
  {
    "상세시설ID": 1152,
    "상세시설명": "월봉중학교 체육관"
  },
  {
    "상세시설ID": 1153,
    "상세시설명": "체육관(어울마루 3층)"
  },
  {
    "상세시설ID": 1154,
    "상세시설명": "다목적교실(해찬나래)"
  },
  {
    "상세시설ID": 1155,
    "상세시설명": "다목적교실(청풍마루)"
  },
  {
    "상세시설ID": 1156,
    "상세시설명": "1층다목적실,2층 회의실"
  },
  {
    "상세시설ID": 1157,
    "상세시설명": "수문초등학교 체육관"
  },
  {
    "상세시설ID": 1158,
    "상세시설명": "신창중학교 체육관"
  },
  {
    "상세시설ID": 1159,
    "상세시설명": "본관 1층~5층"
  },
  {
    "상세시설ID": 1160,
    "상세시설명": "1층 체육관(별관건물)"
  },
  {
    "상세시설ID": 1161,
    "상세시설명": "1~2층 체육관(별관건물)"
  },
  {
    "상세시설ID": 1162,
    "상세시설명": "체육관(해솔관, 별관건물)"
  },
  {
    "상세시설ID": 1163,
    "상세시설명": "다목적실 등"
  },
  {
    "상세시설ID": 1164,
    "상세시설명": "다목적체육관 등"
  },
  {
    "상세시설ID": 1165,
    "상세시설명": "에코롯지 숙박동"
  },
  {
    "상세시설ID": 1166,
    "상세시설명": "혜화홀 3층"
  },
  {
    "상세시설ID": 1167,
    "상세시설명": "예지관 체육관"
  },
  {
    "상세시설ID": 1168,
    "상세시설명": "제천체육관"
  },
  {
    "상세시설ID": 1169,
    "상세시설명": "기성종합복지관"
  },
  {
    "상세시설ID": 1170,
    "상세시설명": "1층 체육관(솔빛관, 별관건물)"
  },
  {
    "상세시설ID": 1171,
    "상세시설명": "2층 체육관(해솔관, 별관)"
  },
  {
    "상세시설ID": 1172,
    "상세시설명": "1층 체육관(다누리관)"
  },
  {
    "상세시설ID": 1173,
    "상세시설명": "4층대강당, 3층 운동실, 3층 3교육실"
  },
  {
    "상세시설ID": 1174,
    "상세시설명": "2층 체육관(솔빛채, 별관건물)"
  },
  {
    "상세시설ID": 1175,
    "상세시설명": "2층 체육관(도담관, 본관)"
  },
  {
    "상세시설ID": 1176,
    "상세시설명": "1~3층 프로그램실, 4층대강당"
  },
  {
    "상세시설ID": 1177,
    "상세시설명": "2층 체육관(별관건물)"
  },
  {
    "상세시설ID": 1178,
    "상세시설명": "강당(교사시설 2층)"
  },
  {
    "상세시설ID": 1179,
    "상세시설명": "체육관(교사시설 2층)"
  },
  {
    "상세시설ID": 1180,
    "상세시설명": "2층 체육관(오성채움관, 별관건물)"
  },
  {
    "상세시설ID": 1181,
    "상세시설명": "1층 도서관(별관), 1~2층교사동(본관),"
  },
  {
    "상세시설ID": 1182,
    "상세시설명": "2층 체육관,"
  },
  {
    "상세시설ID": 1183,
    "상세시설명": "1~5층 일반교실"
  },
  {
    "상세시설ID": 1184,
    "상세시설명": "5층 다목적교실"
  },
  {
    "상세시설ID": 1185,
    "상세시설명": "2~5층 일반교실"
  },
  {
    "상세시설ID": 1186,
    "상세시설명": "3층 체육관(E동)"
  },
  {
    "상세시설ID": 1187,
    "상세시설명": "3층 강당(체육관 겸용, 별관건물)"
  },
  {
    "상세시설ID": 1188,
    "상세시설명": "3층다목적실"
  },
  {
    "상세시설ID": 1189,
    "상세시설명": "프로그램실 등"
  },
  {
    "상세시설ID": 1190,
    "상세시설명": "보람관(체육관)"
  },
  {
    "상세시설ID": 1191,
    "상세시설명": "다목적실(교사시설 5층)"
  },
  {
    "상세시설ID": 1192,
    "상세시설명": "다목적실(교사시설 2층)"
  },
  {
    "상세시설ID": 1193,
    "상세시설명": "강당(교사시설 4층)"
  },
  {
    "상세시설ID": 1194,
    "상세시설명": "강당동(다목적강당 3층)"
  },
  {
    "상세시설ID": 1195,
    "상세시설명": "강당(교사시설 3층)"
  },
  {
    "상세시설ID": 1196,
    "상세시설명": "체육관(늘봄관 2층)"
  },
  {
    "상세시설ID": 1197,
    "상세시설명": "강당(급식소 및 강당동 2층)"
  },
  {
    "상세시설ID": 1198,
    "상세시설명": "강당(교사시설 5층)"
  },
  {
    "상세시설ID": 1199,
    "상세시설명": "체육관, 강의실 등"
  },
  {
    "상세시설ID": 1200,
    "상세시설명": "강당(목련관2층)"
  },
  {
    "상세시설ID": 1201,
    "상세시설명": "경연관(교육시설 2층-강당)"
  },
  {
    "상세시설ID": 1202,
    "상세시설명": "강당(본관 2층)"
  },
  {
    "상세시설ID": 1203,
    "상세시설명": "체육관 강당겸용(교사시설 3층)"
  },
  {
    "상세시설ID": 1204,
    "상세시설명": "다목적실(강당2층)"
  },
  {
    "상세시설ID": 1205,
    "상세시설명": "체육관 강당겸용(교사시설 4층))"
  },
  {
    "상세시설ID": 1206,
    "상세시설명": "분관"
  },
  {
    "상세시설ID": 1207,
    "상세시설명": "수련원, 체육관"
  },
  {
    "상세시설ID": 1208,
    "상세시설명": "솔빛관(숙소)"
  },
  {
    "상세시설ID": 1209,
    "상세시설명": "생활관 A, B동"
  },
  {
    "상세시설ID": 1210,
    "상세시설명": "느티나무홀 3층(강당)"
  },
  {
    "상세시설ID": 1211,
    "상세시설명": "해누리관 2층"
  },
  {
    "상세시설ID": 1212,
    "상세시설명": "본관 5층 다목적실(강당)"
  },
  {
    "상세시설ID": 1213,
    "상세시설명": "덕성관 2층 강당"
  },
  {
    "상세시설ID": 1214,
    "상세시설명": "청사"
  },
  {
    "상세시설ID": 1215,
    "상세시설명": "연수기관"
  },
  {
    "상세시설ID": 1216,
    "상세시설명": "체육관(교사동 2층)"
  },
  {
    "상세시설ID": 1217,
    "상세시설명": "남부문화스포츠센터"
  },
  {
    "상세시설ID": 1218,
    "상세시설명": "고대초등학교 강당"
  },
  {
    "상세시설ID": 1219,
    "상세시설명": "삼봉초등학교 체육관"
  },
  {
    "상세시설ID": 1220,
    "상세시설명": "조금초등학교 체육관"
  },
  {
    "상세시설ID": 1221,
    "상세시설명": "천의초등학교 강당"
  },
  {
    "상세시설ID": 1222,
    "상세시설명": "순성중학교 체육관"
  },
  {
    "상세시설ID": 1223,
    "상세시설명": "순성초등학교 강당"
  },
  {
    "상세시설ID": 1224,
    "상세시설명": "서정초등학교 체육관"
  },
  {
    "상세시설ID": 1225,
    "상세시설명": "체육관(내진양호)"
  },
  {
    "상세시설ID": 1226,
    "상세시설명": "덕지관"
  },
  {
    "상세시설ID": 1227,
    "상세시설명": "급식실,체육관"
  },
  {
    "상세시설ID": 1228,
    "상세시설명": "지하창고"
  },
  {
    "상세시설ID": 1229,
    "상세시설명": "체육관(교사시설 1층)"
  },
  {
    "상세시설ID": 1230,
    "상세시설명": "교회2층"
  },
  {
    "상세시설ID": 1231,
    "상세시설명": "홍제3동주민센터"
  },
  {
    "상세시설ID": 1232,
    "상세시설명": "유곡초등학교 강당"
  },
  {
    "상세시설ID": 1233,
    "상세시설명": "계성초등학교 체육관"
  },
  {
    "상세시설ID": 1234,
    "상세시설명": "당진교육문화스포츠센터"
  },
  {
    "상세시설ID": 1235,
    "상세시설명": "당진중학교"
  },
  {
    "상세시설ID": 1236,
    "상세시설명": "성당초등학교"
  },
  {
    "상세시설ID": 1237,
    "상세시설명": "원당초등학교 체육관"
  },
  {
    "상세시설ID": 1238,
    "상세시설명": "자치센터"
  },
  {
    "상세시설ID": 1239,
    "상세시설명": "장애인복지관"
  },
  {
    "상세시설ID": 1240,
    "상세시설명": "노인복지관"
  },
  {
    "상세시설ID": 1241,
    "상세시설명": "기숙사 2층"
  },
  {
    "상세시설ID": 1242,
    "상세시설명": "다목적강당 2층"
  },
  {
    "상세시설ID": 1243,
    "상세시설명": "다솜리조트"
  },
  {
    "상세시설ID": 1244,
    "상세시설명": "급식실 2층"
  },
  {
    "상세시설ID": 1245,
    "상세시설명": "다목적교실 1층"
  },
  {
    "상세시설ID": 1246,
    "상세시설명": "다목적교실 1실"
  },
  {
    "상세시설ID": 1247,
    "상세시설명": "문기초등학교 2층 체육관, 강당"
  },
  {
    "상세시설ID": 1248,
    "상세시설명": "공도초등학교 2층 체육관, 강당"
  },
  {
    "상세시설ID": 1249,
    "상세시설명": "신관(다목적체육회관)"
  },
  {
    "상세시설ID": 1250,
    "상세시설명": "명지대방목학술정보관"
  },
  {
    "상세시설ID": 1251,
    "상세시설명": "어울초등학교 2층 체육관"
  },
  {
    "상세시설ID": 1252,
    "상세시설명": "장서2리경로당"
  },
  {
    "상세시설ID": 1253,
    "상세시설명": "미곡초등학교 후관동 2층 다목적실"
  },
  {
    "상세시설ID": 1254,
    "상세시설명": "2층 체육관 다목적실"
  },
  {
    "상세시설ID": 1255,
    "상세시설명": "일죽행정복지센터 3층 다목적홀"
  },
  {
    "상세시설ID": 1256,
    "상세시설명": "강당(본관 5층)"
  },
  {
    "상세시설ID": 1257,
    "상세시설명": "비룡초등학교 체육관"
  },
  {
    "상세시설ID": 1258,
    "상세시설명": "안성여자고등학교 체육관(터울림관)"
  },
  {
    "상세시설ID": 1259,
    "상세시설명": "공도중학교 1층 체육관"
  },
  {
    "상세시설ID": 1260,
    "상세시설명": "만정초등학교 2층 다목적 강당"
  },
  {
    "상세시설ID": 1261,
    "상세시설명": "공도읍행정복지센터 2층 다목적홀"
  },
  {
    "상세시설ID": 1262,
    "상세시설명": "만정중학교 체육관"
  },
  {
    "상세시설ID": 1263,
    "상세시설명": "경기창조고등학교 2층 체육관"
  },
  {
    "상세시설ID": 1264,
    "상세시설명": "양진중학교 2층 체육관"
  },
  {
    "상세시설ID": 1265,
    "상세시설명": "보개초등학교 3층 강당"
  },
  {
    "상세시설ID": 1266,
    "상세시설명": "동신초등학교 체육관(해빛관)"
  },
  {
    "상세시설ID": 1267,
    "상세시설명": "개산초등학교 1층 체육관(모룻돌 체육관)"
  },
  {
    "상세시설ID": 1268,
    "상세시설명": "9호동 2층 체육관"
  },
  {
    "상세시설ID": 1269,
    "상세시설명": "서운중학교 강당"
  },
  {
    "상세시설ID": 1270,
    "상세시설명": "별관 2층 도서실"
  },
  {
    "상세시설ID": 1271,
    "상세시설명": "서운초등학교 체육관"
  },
  {
    "상세시설ID": 1272,
    "상세시설명": "개정초등학교 2층 강당"
  },
  {
    "상세시설ID": 1273,
    "상세시설명": "미양초등학교 체육관"
  },
  {
    "상세시설ID": 1274,
    "상세시설명": "두원공업고등학교 다목적체육관"
  },
  {
    "상세시설ID": 1275,
    "상세시설명": "대덕초등학교 체육관"
  },
  {
    "상세시설ID": 1276,
    "상세시설명": "명덕초등학교 체육관"
  },
  {
    "상세시설ID": 1277,
    "상세시설명": "죽화초등학교 배움누리터 강당"
  },
  {
    "상세시설ID": 1278,
    "상세시설명": "죽산초등학교 1층 체육관, 강당"
  },
  {
    "상세시설ID": 1279,
    "상세시설명": "해솔관 체육관"
  },
  {
    "상세시설ID": 1280,
    "상세시설명": "두원공과대학교 천마체육관 1층 경기장"
  },
  {
    "상세시설ID": 1281,
    "상세시설명": "한겨례고등학교 1층 체육관"
  },
  {
    "상세시설ID": 1282,
    "상세시설명": "광선초등학교 교사2동 1층 다목적실"
  },
  {
    "상세시설ID": 1283,
    "상세시설명": "삼죽초등학교 체육관"
  },
  {
    "상세시설ID": 1284,
    "상세시설명": "고삼초등학교 1층 다목적실"
  },
  {
    "상세시설ID": 1285,
    "상세시설명": "안성여자중학교 비솔체육관"
  },
  {
    "상세시설ID": 1286,
    "상세시설명": "안성초등학교 강당"
  },
  {
    "상세시설ID": 1287,
    "상세시설명": "명륜여자중학교 2층 다목적실"
  },
  {
    "상세시설ID": 1288,
    "상세시설명": "가온고등학교 체육관"
  },
  {
    "상세시설ID": 1289,
    "상세시설명": "한경대학교 체육관 1층 104호"
  },
  {
    "상세시설ID": 1290,
    "상세시설명": "내혜홀초등학교 2층 체육관"
  },
  {
    "상세시설ID": 1291,
    "상세시설명": "백성초등학교 2층 체육관"
  },
  {
    "상세시설ID": 1292,
    "상세시설명": "안성고등학교 체육관(1층)"
  },
  {
    "상세시설ID": 1293,
    "상세시설명": "비룡중학교 청솔관 체육관(2층)"
  },
  {
    "상세시설ID": 1294,
    "상세시설명": "안청중학교 체육관"
  },
  {
    "상세시설ID": 1295,
    "상세시설명": "3층 수주마당"
  },
  {
    "상세시설ID": 1296,
    "상세시설명": "6층"
  }
]